{"episode_idx":705,"task_id":1,"seed":747,"split":"train","batch":{"gstin":"10YDLHN7100K7ZA","tax_period":"2023-05","invoices":[{"invoice_id":"INV-2023-05-0000","supplier_gstin":"01LNSYO7406Q7Z9","buyer_gstin":"10YDLHN7100K7ZA","invoice_date":"2023-05-15","invoice_type":"B2B","hsn_code":"2101","description":"Extracts of Coffee","taxable_value":116888.3,"igst_amount":21039.89,"cgst_amount":0.0,"sgst_amount":0.0,"total_amount":137928.19,"gstr2b_match":null,"status":"pending","flags":[]},{"invoice_id":"INV-2023-05-0001","supplier_gstin":"18CFTRZ1659F4Z8","buyer_gstin":"10YDLHN7100K7ZA","invoice_date":"2023-05-23","invoice_type":"B2B","hsn_code":"9003","description":"Spectacle Frames","taxable_value":54128.12,"igst_amount":6495.37,"cgst_amount":0.0,"sgst_amount":0.0,"total_amount":60623.49,"gstr2b_match":null,"status":"pending","flags":[]},{"invoice_id":"INV-2023-05-0002","supplier_gstin":"29YVIQS0348YAZ6","buyer_gstin":"10YDLHN7100K7ZA","invoice_date":"2023-05-18","invoice_type":"RCM","hsn_code":"9101","description":"Wrist-Watches with Precious Metal","taxable_value":177270.32,"igst_amount":31908.66,"cgst_amount":0.0,"sgst_amount":0.0,"total_amount":209178.98,"gstr2b_match":null,"status":"pending","flags":["fake_invoice"]},{"invoice_id":"INV-2023-05-0003","supplier_gstin":null,"buyer_gstin":"10YDLHN7100K7ZA","invoice_date":"2023-05-27","invoice_type":"B2C","hsn_code":"9003","description":"Spectacle Frames","taxable_value":50442.54,"igst_amount":6053.1,"cgst_amount":0.0,"sgst_amount":0.0,"total_amount":56495.64,"gstr2b_match":null,"status":"pending","flags":["missing_gstin"]},{"invoice_id":"INV-2023-05-0004","supplier_gstin":"17EGHBP1585W3ZR","buyer_gstin":"10YDLHN7100K7ZA","invoice_date":"2023-05-15","invoice_type":"RCM","hsn_code":"8708","description":"Parts for Motor Vehicles","taxable_value":106622.49,"igst_amount":29854.3,"cgst_amount":0.0,"sgst_amount":0.0,"total_amount":136476.79,"gstr2b_match":null,"status":"pending","flags":["fake_invoice"]},{"invoice_id":"INV-2023-05-0005","supplier_gstin":"14FYUPB2968L2ZL","buyer_gstin":"10YDLHN7100K7ZA","invoice_date":"2023-05-02","invoice_type":"B2B","hsn_code":"2201","description":"Waters, Including Natural","taxable_value":59018.74,"igst_amount":10623.37,"cgst_amount":0.0,"sgst_amount":0.0,"total_amount":69642.11,"gstr2b_match":null,"status":"pending","flags":[]},{"invoice_id":"INV-2023-05-0006","supplier_gstin":"29UUXSA7564Q3ZH","buyer_gstin":"10YDLHN7100K7ZA","invoice_date":"2023-05-05","invoice_type":"EXPORT","hsn_code":"2501","description":"Salt","taxable_value":160699.32,"igst_amount":0.0,"cgst_amount":0.0,"sgst_amount":0.0,"total_amount":160699.32,"gstr2b_match":null,"status":"pending","flags":[]},{"invoice_id":"INV-2023-05-0007","supplier_gstin":"11RUWLW0003ICZY","buyer_gstin":"10YDLHN7100K7ZA","invoice_date":"2023-05-20","invoice_type":"B2B","hsn_code":"7001","description":"Cullet and Other Waste Glass","taxable_value":161857.05,"igst_amount":29134.27,"cgst_amount":0.0,"sgst_amount":0.0,"total_amount":190991.32,"gstr2b_match":null,"status":"pending","flags":[]},{"invoice_id":"INV-2023-05-0008","supplier_gstin":"02BSSPM6629GDZY","buyer_gstin":"10YDLHN7100K7ZA","invoice_date":"2023-05-16","invoice_type":"B2C","hsn_code":"2917","description":"Polycarboxylic Acids","taxable_value":69043.59,"igst_amount":12427.85,"cgst_amount":0.0,"sgst_amount":0.0,"total_amount":81471.44,"gstr2b_match":null,"status":"pending","flags":[]},{"invoice_id":"INV-2023-05-0009","supplier_gstin":"22GUBOA4016N3ZV","buyer_gstin":"10YDLHN7100K7ZA","invoice_date":"2023-05-17","invoice_type":"EXPORT","hsn_code":"9993","description":"Human Health Services","taxable_value":176936.94,"igst_amount":0.0,"cgst_amount":0.0,"sgst_amount":0.0,"total_amount":176936.94,"gstr2b_match":null,"status":"pending","flags":["fake_invoice"]},{"invoice_id":"INV-2023-05-0010","supplier_gstin":"02KVAJU0309CEZW","buyer_gstin":"10YDLHN7100K7ZA","invoice_date":"2023-05-04","invoice_type":"B2C","hsn_code":"9401","description":"Seats","taxable_value":69026.51,"igst_amount":19327.42,"cgst_amount":0.0,"sgst_amount":0.0,"total_amount":88353.93,"gstr2b_match":null,"status":"pending","flags":[]},{"invoice_id":"INV-2023-05-0011","supplier_gstin":"36PZTRX6869A2ZR","buyer_gstin":"10YDLHN7100K7ZA","invoice_date":"2023-05-10","invoice_type":"B2C","hsn_code":"8517","description":"Telephone Sets and Mobile Phones","taxable_value":115832.72,"igst_amount":20849.89,"cgst_amount":0.0,"sgst_amount":0.0,"total_amount":136682.61,"gstr2b_match":null,"status":"pending","flags":[]},{"invoice_id":"INV-2023-05-0012","supplier_gstin":"29RABIM7322BDZH","buyer_gstin":"10YDLHN7100K7ZA","invoice_date":"2023-05-06","invoice_type":"B2B","hsn_code":"9601","description":"Worked Ivory","taxable_value":102062.05,"igst_amount":12247.45,"cgst_amount":0.0,"sgst_amount":0.0,"total_amount":114309.5,"gstr2b_match":null,"status":"pending","flags":[]},{"invoice_id":"INV-2023-05-0013","supplier_gstin":"06GLAIU9120R6ZH","buyer_gstin":"10YDLHN7100K7ZA","invoice_date":"2023-05-23","invoice_type":"EXPORT","hsn_code":"1101","description":"Wheat Flour","taxable_value":116251.83,"igst_amount":0.0,"cgst_amount":0.0,"sgst_amount":0.0,"total_amount":116251.83,"gstr2b_match":null,"status":"pending","flags":[]},{"invoice_id":"INV-2023-05-0014","supplier_gstin":"07YREPS5544MCZ4","buyer_gstin":"10YDLHN7100K7ZA","invoice_date":"2023-05-11","invoice_type":"RCM","hsn_code":"8407","description":"Spark-Ignition Engines","taxable_value":68334.21,"igst_amount":19133.58,"cgst_amount":0.0,"sgst_amount":0.0,"total_amount":87467.79,"gstr2b_match":null,"status":"pending","flags":[]},{"invoice_id":"INV-2023-05-0015","supplier_gstin":"23MAVRP1449RDZV","buyer_gstin":"10YDLHN7100K7ZA","invoice_date":"2023-05-25","invoice_type":"EXPORT","hsn_code":"6801","description":"Setts, Curbstones, Flagstones","taxable_value":122027.6,"igst_amount":6101.38,"cgst_amount":0.0,"sgst_amount":0.0,"total_amount":128128.98,"gstr2b_match":null,"status":"pending","flags":[]},{"invoice_id":"INV-2023-05-0016","supplier_gstin":"30MTGKC4122JDZT","buyer_gstin":"10YDLHN7100K7ZA","invoice_date":"2023-05-23","invoice_type":"B2B","hsn_code":"9701","description":"Paintings and Drawings","taxable_value":119213.93,"igst_amount":14305.67,"cgst_amount":0.0,"sgst_amount":0.0,"total_amount":133519.6,"gstr2b_match":null,"status":"pending","flags":[]},{"invoice_id":"INV-2023-05-0017","supplier_gstin":"14WQOZN2291B5ZJ","buyer_gstin":"10YDLHN7100K7ZA","invoice_date":"2023-05-04","invoice_type":"EXPORT","hsn_code":"4202","description":"Trunks, Suitcases, Handbags","taxable_value":77979.72,"igst_amount":21834.32,"cgst_amount":0.0,"sgst_amount":0.0,"total_amount":99814.04,"gstr2b_match":null,"status":"pending","flags":[]},{"invoice_id":"INV-2023-05-0018","supplier_gstin":"09KUSCK9221NEZQ","buyer_gstin":"10YDLHN7100K7ZA","invoice_date":"2023-05-13","invoice_type":"EXPORT","hsn_code":"5101","description":"Wool, not Carded","taxable_value":10540.28,"igst_amount":527.01,"cgst_amount":0.0,"sgst_amount":0.0,"total_amount":11067.29,"gstr2b_match":null,"status":"pending","flags":[]},{"invoice_id":"INV-2023-05-0019","supplier_gstin":"13RBQWK0673O9Z0","buyer_gstin":"10YDLHN7100K7ZA","invoice_date":"2023-05-06","invoice_type":"B2B","hsn_code":"9503","description":"Tricycles and Toy Vehicles","taxable_value":25124.65,"igst_amount":3014.96,"cgst_amount":0.0,"sgst_amount":0.0,"total_amount":28139.61,"gstr2b_match":null,"status":"pending","flags":[]}],"ground_truth":{"INV-2023-05-0000":{"invoice_id":"INV-2023-05-0000","invoice_type":"B2B","hsn_code":"2101","gst_slab":"18","supply_type":"goods","itc_eligible":true,"reverse_charge":false},"INV-2023-05-0001":{"invoice_id":"INV-2023-05-0001","invoice_type":"B2B","hsn_code":"9003","gst_slab":"12","supply_type":"goods","itc_eligible":true,"reverse_charge":false},"INV-2023-05-0002":{"invoice_id":"INV-2023-05-0002","invoice_type":"RCM","hsn_code":"9101","gst_slab":"18","supply_type":"goods","itc_eligible":false,"reverse_charge":true},"INV-2023-05-0003":{"invoice_id":"INV-2023-05-0003","invoice_type":"B2C","hsn_code":"9003","gst_slab":"12","supply_type":"goods","itc_eligible":false,"reverse_charge":false},"INV-2023-05-0004":{"invoice_id":"INV-2023-05-0004","invoice_type":"RCM","hsn_code":"8708","gst_slab":"28","supply_type":"goods","itc_eligible":false,"reverse_charge":true},"INV-2023-05-0005":{"invoice_id":"INV-2023-05-0005","invoice_type":"B2B","hsn_code":"2201","gst_slab":"18","supply_type":"goods","itc_eligible":true,"reverse_charge":false},"INV-2023-05-0006":{"invoice_id":"INV-2023-05-0006","invoice_type":"EXPORT","hsn_code":"2501","gst_slab":"0","supply_type":"goods","itc_eligible":false,"reverse_charge":false},"INV-2023-05-0007":{"invoice_id":"INV-2023-05-0007","invoice_type":"B2B","hsn_code":"7001","gst_slab":"18","supply_type":"goods","itc_eligible":true,"reverse_charge":false},"INV-2023-05-0008":{"invoice_id":"INV-2023-05-0008","invoice_type":"B2C","hsn_code":"2917","gst_slab":"18","supply_type":"goods","itc_eligible":false,"reverse_charge":false},"INV-2023-05-0009":{"invoice_id":"INV-2023-05-0009","invoice_type":"EXPORT","hsn_code":"9993","gst_slab":"0","supply_type":"services","itc_eligible":false,"reverse_charge":false},"INV-2023-05-0010":{"invoice_id":"INV-2023-05-0010","invoice_type":"B2C","hsn_code":"9401","gst_slab":"28","supply_type":"goods","itc_eligible":false,"reverse_charge":false},"INV-2023-05-0011":{"invoice_id":"INV-2023-05-0011","invoice_type":"B2C","hsn_code":"8517","gst_slab":"18","supply_type":"goods","itc_eligible":false,"reverse_charge":false},"INV-2023-05-0012":{"invoice_id":"INV-2023-05-0012","invoice_type":"B2B","hsn_code":"9601","gst_slab":"12","supply_type":"goods","itc_eligible":true,"reverse_charge":false},"INV-2023-05-0013":{"invoice_id":"INV-2023-05-0013","invoice_type":"EXPORT","hsn_code":"1101","gst_slab":"0","supply_type":"goods","itc_eligible":false,"reverse_charge":false},"INV-2023-05-0014":{"invoice_id":"INV-2023-05-0014","invoice_type":"RCM","hsn_code":"8407","gst_slab":"28","supply_type":"goods","itc_eligible":true,"reverse_charge":true},"INV-2023-05-0015":{"invoice_id":"INV-2023-05-0015","invoice_type":"EXPORT","hsn_code":"6801","gst_slab":"5","supply_type":"goods","itc_eligible":false,"reverse_charge":false},"INV-2023-05-0016":{"invoice_id":"INV-2023-05-0016","invoice_type":"B2B","hsn_code":"9701","gst_slab":"12","supply_type":"goods","itc_eligible":true,"reverse_charge":false},"INV-2023-05-0017":{"invoice_id":"INV-2023-05-0017","invoice_type":"EXPORT","hsn_code":"4202","gst_slab":"28","supply_type":"goods","itc_eligible":false,"reverse_charge":false},"INV-2023-05-0018":{"invoice_id":"INV-2023-05-0018","invoice_type":"EXPORT","hsn_code":"5101","gst_slab":"5","supply_type":"goods","itc_eligible":false,"reverse_charge":false},"INV-2023-05-0019":{"invoice_id":"INV-2023-05-0019","invoice_type":"B2B","hsn_code":"9503","gst_slab":"12","supply_type":"goods","itc_eligible":true,"reverse_charge":false}},"supplier_profiles":{"01LNSYO7406Q7Z9":{"compliance_rate":0.8946,"avg_delay_days":0.7,"cancelled_pct":0.0206},"18CFTRZ1659F4Z8":{"compliance_rate":0.994,"avg_delay_days":6.5,"cancelled_pct":0.0261},"29YVIQS0348YAZ6":{"compliance_rate":0.9586,"avg_delay_days":7.3,"cancelled_pct":0.036},"17EGHBP1585W3ZR":{"compliance_rate":0.9715,"avg_delay_days":0.3,"cancelled_pct":0.0235},"14FYUPB2968L2ZL":{"compliance_rate":0.8257,"avg_delay_days":12.6,"cancelled_pct":0.0196},"29UUXSA7564Q3ZH":{"compliance_rate":0.8977,"avg_delay_days":6.5,"cancelled_pct":0.0084},"11RUWLW0003ICZY":{"compliance_rate":0.921,"avg_delay_days":10.6,"cancelled_pct":0.0404},"02BSSPM6629GDZY":{"compliance_rate":0.8573,"avg_delay_days":3.0,"cancelled_pct":0.0499},"22GUBOA4016N3ZV":{"compliance_rate":0.9733,"avg_delay_days":0.1,"cancelled_pct":0.0127},"02KVAJU0309CEZW":{"compliance_rate":0.9097,"avg_delay_days":6.1,"cancelled_pct":0.0349},"36PZTRX6869A2ZR":{"compliance_rate":0.9295,"avg_delay_days":8.6,"cancelled_pct":0.0354},"29RABIM7322BDZH":{"compliance_rate":0.8197,"avg_delay_days":9.5,"cancelled_pct":0.0171},"06GLAIU9120R6ZH":{"compliance_rate":0.8894,"avg_delay_days":1.9,"cancelled_pct":0.034},"07YREPS5544MCZ4":{"compliance_rate":0.8754,"avg_delay_days":1.3,"cancelled_pct":0.0494},"23MAVRP1449RDZV":{"compliance_rate":0.9604,"avg_delay_days":14.3,"cancelled_pct":0.0017},"30MTGKC4122JDZT":{"compliance_rate":0.8257,"avg_delay_days":14.1,"cancelled_pct":0.0245},"14WQOZN2291B5ZJ":{"compliance_rate":0.9935,"avg_delay_days":3.0,"cancelled_pct":0.0199},"09KUSCK9221NEZQ":{"compliance_rate":0.8765,"avg_delay_days":2.2,"cancelled_pct":0.0304},"13RBQWK0673O9Z0":{"compliance_rate":0.9593,"avg_delay_days":3.8,"cancelled_pct":0.0415}},"eligible_itc":197062.43}}