{"episode_idx":712,"task_id":2,"seed":754,"split":"train","batch":{"gstin":"06TXQER0152O2ZU","tax_period":"2024-11","invoices":[{"invoice_id":"INV-2024-11-0000","supplier_gstin":"04DMJMK9522DEZT","buyer_gstin":"06TXQER0152O2ZU","invoice_date":"2024-11-27","invoice_type":"B2B","hsn_code":"9995","description":"Membership Organization Services","taxable_value":10582.68,"igst_amount":1904.88,"cgst_amount":0.0,"sgst_amount":0.0,"total_amount":12487.56,"gstr2b_match":null,"status":"pending","flags":[]},{"invoice_id":"INV-2024-11-0001","supplier_gstin":"33AKIAN5398A8ZO","buyer_gstin":"06TXQER0152O2ZU","invoice_date":"2024-11-11","invoice_type":"EXPORT","hsn_code":"6601","description":"Umbrellas","taxable_value":68979.49,"igst_amount":8277.54,"cgst_amount":0.0,"sgst_amount":0.0,"total_amount":77257.03,"gstr2b_match":null,"status":"pending","flags":[]},{"invoice_id":"INV-2024-11-0002","supplier_gstin":"21UNCLS1753F9ZN","buyer_gstin":"06TXQER0152O2ZU","invoice_date":"2024-11-22","invoice_type":"B2B","hsn_code":"9984","description":"Telecommunications Services","taxable_value":63295.28,"igst_amount":11393.15,"cgst_amount":0.0,"sgst_amount":0.0,"total_amount":74688.43,"gstr2b_match":null,"status":"pending","flags":[]},{"invoice_id":"INV-2024-11-0003","supplier_gstin":"21BSIVA2380DDZN","buyer_gstin":"06TXQER0152O2ZU","invoice_date":"2024-11-14","invoice_type":"B2B","hsn_code":"9201","description":"Pianos","taxable_value":110638.78,"igst_amount":30978.86,"cgst_amount":0.0,"sgst_amount":0.0,"total_amount":141617.64,"gstr2b_match":null,"status":"pending","flags":[]},{"invoice_id":"INV-2024-11-0004","supplier_gstin":"34HMNBZ5870O8Z6","buyer_gstin":"06TXQER0152O2ZU","invoice_date":"2024-11-13","invoice_type":"EXPORT","hsn_code":"7304","description":"Tubes and Pipes of Iron/Steel","taxable_value":60213.08,"igst_amount":10838.35,"cgst_amount":0.0,"sgst_amount":0.0,"total_amount":71051.43,"gstr2b_match":null,"status":"pending","flags":[]},{"invoice_id":"INV-2024-11-0005","supplier_gstin":"29RLPTG6380J4ZK","buyer_gstin":"06TXQER0152O2ZU","invoice_date":"2024-11-20","invoice_type":"B2C","hsn_code":"8703","description":"Motor Cars","taxable_value":137242.83,"igst_amount":38427.99,"cgst_amount":0.0,"sgst_amount":0.0,"total_amount":175670.82,"gstr2b_match":null,"status":"pending","flags":[]},{"invoice_id":"INV-2024-11-0006","supplier_gstin":"21XLAVT4578L0ZO","buyer_gstin":"06TXQER0152O2ZU","invoice_date":"2024-11-12","invoice_type":"B2B","hsn_code":"0301","description":"Live Fish","taxable_value":102603.06,"igst_amount":0.0,"cgst_amount":0.0,"sgst_amount":0.0,"total_amount":102603.06,"gstr2b_match":null,"status":"pending","flags":[]},{"invoice_id":"INV-2024-11-0007","supplier_gstin":"36SZWBL2332ADZA","buyer_gstin":"06TXQER0152O2ZU","invoice_date":"2024-11-10","invoice_type":"B2B","hsn_code":"9999","description":"Services by Extraterritorial Orgs","taxable_value":34267.57,"igst_amount":0.0,"cgst_amount":0.0,"sgst_amount":0.0,"total_amount":34267.57,"gstr2b_match":null,"status":"pending","flags":[]},{"invoice_id":"INV-2024-11-0008","supplier_gstin":"30CTFID8513W5ZE","buyer_gstin":"06TXQER0152O2ZU","invoice_date":"2024-11-13","invoice_type":"B2B","hsn_code":"9984","description":"Telecommunications Services","taxable_value":43395.49,"igst_amount":7811.19,"cgst_amount":0.0,"sgst_amount":0.0,"total_amount":51206.68,"gstr2b_match":null,"status":"pending","flags":[]},{"invoice_id":"INV-2024-11-0009","supplier_gstin":"17YXYIW9984X3ZI","buyer_gstin":"06TXQER0152O2ZU","invoice_date":"2024-11-03","invoice_type":"B2B","hsn_code":"9997","description":"Other Personal Services","taxable_value":8092.68,"igst_amount":1456.68,"cgst_amount":0.0,"sgst_amount":0.0,"total_amount":9549.36,"gstr2b_match":null,"status":"pending","flags":[]},{"invoice_id":"INV-2024-11-0010","supplier_gstin":"34NCNHD3279S8ZN","buyer_gstin":"06TXQER0152O2ZU","invoice_date":"2024-11-22","invoice_type":"B2B","hsn_code":"3401","description":"Soap","taxable_value":11298.83,"igst_amount":2033.79,"cgst_amount":0.0,"sgst_amount":0.0,"total_amount":13332.62,"gstr2b_match":null,"status":"pending","flags":[]},{"invoice_id":"INV-2024-11-0011","supplier_gstin":"20YSGNF1947S0ZU","buyer_gstin":"06TXQER0152O2ZU","invoice_date":"2024-11-20","invoice_type":"B2B","hsn_code":"8525","description":"Transmission Apparatus for TV","taxable_value":53460.43,"igst_amount":9622.88,"cgst_amount":0.0,"sgst_amount":0.0,"total_amount":63083.31,"gstr2b_match":null,"status":"pending","flags":[]},{"invoice_id":"INV-2024-11-0012","supplier_gstin":"29KYGYW0939E5Z0","buyer_gstin":"06TXQER0152O2ZU","invoice_date":"2024-11-09","invoice_type":"RCM","hsn_code":"9201","description":"Pianos","taxable_value":50961.94,"igst_amount":14269.34,"cgst_amount":0.0,"sgst_amount":0.0,"total_amount":65231.28,"gstr2b_match":null,"status":"pending","flags":[]},{"invoice_id":"INV-2024-11-0013","supplier_gstin":"23VLMRQ4368E4Z0","buyer_gstin":"06TXQER0152O2ZU","invoice_date":"2024-11-13","invoice_type":"B2C","hsn_code":"6301","description":"Blankets and Travelling Rugs","taxable_value":144995.91,"igst_amount":17399.51,"cgst_amount":0.0,"sgst_amount":0.0,"total_amount":162395.42,"gstr2b_match":null,"status":"pending","flags":[]},{"invoice_id":"INV-2024-11-0014","supplier_gstin":"07RQLUC2178CDZV","buyer_gstin":"06TXQER0152O2ZU","invoice_date":"2024-11-03","invoice_type":"B2C","hsn_code":"4016","description":"Articles of Rubber","taxable_value":74247.84,"igst_amount":13364.61,"cgst_amount":0.0,"sgst_amount":0.0,"total_amount":87612.45,"gstr2b_match":null,"status":"pending","flags":[]},{"invoice_id":"INV-2024-11-0015","supplier_gstin":"34TLJNG3920F2ZW","buyer_gstin":"06TXQER0152O2ZU","invoice_date":"2024-11-09","invoice_type":"B2C","hsn_code":"9986","description":"Agriculture Support Services","taxable_value":31021.76,"igst_amount":0.0,"cgst_amount":0.0,"sgst_amount":0.0,"total_amount":31021.76,"gstr2b_match":null,"status":"pending","flags":[]},{"invoice_id":"INV-2024-11-0016","supplier_gstin":"06QYFGT9916G2ZU","buyer_gstin":"06TXQER0152O2ZU","invoice_date":"2024-11-21","invoice_type":"B2B","hsn_code":"4407","description":"Wood Sawn or Chipped","taxable_value":11122.37,"igst_amount":0.0,"cgst_amount":667.34,"sgst_amount":667.34,"total_amount":12457.05,"gstr2b_match":null,"status":"pending","flags":[]},{"invoice_id":"INV-2024-11-0017","supplier_gstin":"24ITDBQ7452T9Z2","buyer_gstin":"06TXQER0152O2ZU","invoice_date":"2024-11-26","invoice_type":"B2B","hsn_code":"8544","description":"Insulated Wire and Cable","taxable_value":85401.68,"igst_amount":15372.3,"cgst_amount":0.0,"sgst_amount":0.0,"total_amount":100773.98,"gstr2b_match":null,"status":"pending","flags":[]},{"invoice_id":"INV-2024-11-0018","supplier_gstin":"13RTRND1357F5ZB","buyer_gstin":"06TXQER0152O2ZU","invoice_date":"2024-11-05","invoice_type":"B2B","hsn_code":"0901","description":"Coffee","taxable_value":145166.09,"igst_amount":7258.3,"cgst_amount":0.0,"sgst_amount":0.0,"total_amount":152424.39,"gstr2b_match":null,"status":"pending","flags":[]},{"invoice_id":"INV-2024-11-0019","supplier_gstin":"34RTPFD7952V5ZF","buyer_gstin":"06TXQER0152O2ZU","invoice_date":"2024-11-02","invoice_type":"B2B","hsn_code":"8601","description":"Rail Locomotives","taxable_value":84815.69,"igst_amount":10177.88,"cgst_amount":0.0,"sgst_amount":0.0,"total_amount":94993.57,"gstr2b_match":null,"status":"pending","flags":[]},{"invoice_id":"INV-2024-11-0020","supplier_gstin":"02FQYUT1627SBZ1","buyer_gstin":"06TXQER0152O2ZU","invoice_date":"2024-11-06","invoice_type":"B2C","hsn_code":"3701","description":"Photographic Plates and Film","taxable_value":43225.17,"igst_amount":7780.53,"cgst_amount":0.0,"sgst_amount":0.0,"total_amount":51005.7,"gstr2b_match":null,"status":"pending","flags":[]},{"invoice_id":"INV-2024-11-0021","supplier_gstin":"06PRAFT3787R5ZQ","buyer_gstin":"06TXQER0152O2ZU","invoice_date":"2024-11-10","invoice_type":"B2B","hsn_code":"0201","description":"Beef, Fresh or Chilled","taxable_value":97266.65,"igst_amount":0.0,"cgst_amount":0.0,"sgst_amount":0.0,"total_amount":97266.65,"gstr2b_match":null,"status":"pending","flags":[]},{"invoice_id":"INV-2024-11-0022","supplier_gstin":"01NDHZD6385N3ZA","buyer_gstin":"06TXQER0152O2ZU","invoice_date":"2024-11-25","invoice_type":"B2B","hsn_code":"7001","description":"Cullet and Other Waste Glass","taxable_value":134173.55,"igst_amount":24151.24,"cgst_amount":0.0,"sgst_amount":0.0,"total_amount":158324.79,"gstr2b_match":null,"status":"pending","flags":[]},{"invoice_id":"INV-2024-11-0023","supplier_gstin":"06WQUPO6841Y8ZB","buyer_gstin":"06TXQER0152O2ZU","invoice_date":"2024-11-10","invoice_type":"B2B","hsn_code":"6401","description":"Waterproof Footwear","taxable_value":11800.44,"igst_amount":0.0,"cgst_amount":1062.04,"sgst_amount":1062.04,"total_amount":13924.52,"gstr2b_match":null,"status":"pending","flags":[]},{"invoice_id":"INV-2024-11-0024","supplier_gstin":"15QGVBT5932T3Z7","buyer_gstin":"06TXQER0152O2ZU","invoice_date":"2024-11-07","invoice_type":"EXPORT","hsn_code":"2402","description":"Cigars and Cigarettes","taxable_value":100491.17,"igst_amount":28137.53,"cgst_amount":0.0,"sgst_amount":0.0,"total_amount":128628.7,"gstr2b_match":null,"status":"pending","flags":[]},{"invoice_id":"INV-2024-11-0025","supplier_gstin":"18PJZWY2659QBZB","buyer_gstin":"06TXQER0152O2ZU","invoice_date":"2024-11-22","invoice_type":"B2B","hsn_code":"8544","description":"Insulated Wire and Cable","taxable_value":22013.46,"igst_amount":3962.42,"cgst_amount":0.0,"sgst_amount":0.0,"total_amount":25975.88,"gstr2b_match":null,"status":"pending","flags":[]},{"invoice_id":"INV-2024-11-0026","supplier_gstin":"24RPVTE5187T2ZW","buyer_gstin":"06TXQER0152O2ZU","invoice_date":"2024-11-02","invoice_type":"B2C","hsn_code":"8544","description":"Insulated Wire and Cable","taxable_value":129568.15,"igst_amount":23322.27,"cgst_amount":0.0,"sgst_amount":0.0,"total_amount":152890.42,"gstr2b_match":null,"status":"pending","flags":[]},{"invoice_id":"INV-2024-11-0027","supplier_gstin":"27XIPRL4777Q1Z7","buyer_gstin":"06TXQER0152O2ZU","invoice_date":"2024-11-25","invoice_type":"B2B","hsn_code":"9999","description":"Services by Extraterritorial Orgs","taxable_value":158286.24,"igst_amount":0.0,"cgst_amount":0.0,"sgst_amount":0.0,"total_amount":158286.24,"gstr2b_match":null,"status":"pending","flags":[]},{"invoice_id":"INV-2024-11-0028","supplier_gstin":"05LIYCP2777QAZ2","buyer_gstin":"06TXQER0152O2ZU","invoice_date":"2024-11-05","invoice_type":"B2B","hsn_code":"8703","description":"Motor Cars","taxable_value":193153.71,"igst_amount":54083.04,"cgst_amount":0.0,"sgst_amount":0.0,"total_amount":247236.75,"gstr2b_match":null,"status":"pending","flags":[]},{"invoice_id":"INV-2024-11-0029","supplier_gstin":"30JUWYB7834BEZK","buyer_gstin":"06TXQER0152O2ZU","invoice_date":"2024-11-25","invoice_type":"B2B","hsn_code":"2804","description":"Hydrogen and Noble Gases","taxable_value":138033.42,"igst_amount":6901.67,"cgst_amount":0.0,"sgst_amount":0.0,"total_amount":144935.09,"gstr2b_match":null,"status":"pending","flags":[]}],"purchase_map":{"INV-2024-11-0000":{"invoice_id":"INV-2024-11-0000","invoice_number":"INV-2024-11-0000","supplier_gstin":"04DMJMK9522DEZT","taxable_value":10582.68,"igst_amount":1904.88,"invoice_date":"2024-11-27","hsn_code":"9995"},"INV-2024-11-0001":{"invoice_id":"INV-2024-11-0001","invoice_number":"INV-2024-11-0001","supplier_gstin":"33AKIAN5398A8ZO","taxable_value":68979.49,"igst_amount":8277.54,"invoice_date":"2024-11-11","hsn_code":"6601"},"INV-2024-11-0002":{"invoice_id":"INV-2024-11-0002","invoice_number":"INV-2024-11-0002","supplier_gstin":"21UNCLS1753F9ZN","taxable_value":63295.28,"igst_amount":11393.15,"invoice_date":"2024-11-22","hsn_code":"9984"},"INV-2024-11-0003":{"invoice_id":"INV-2024-11-0003","invoice_number":"INV-2024-11-0003","supplier_gstin":"21BSIVA2380DDZN","taxable_value":110638.78,"igst_amount":30978.86,"invoice_date":"2024-11-14","hsn_code":"9201"},"INV-2024-11-0004":{"invoice_id":"INV-2024-11-0004","invoice_number":"INV-2024-11-0004","supplier_gstin":"34HMNBZ5870O8Z6","taxable_value":60213.08,"igst_amount":10838.35,"invoice_date":"2024-11-13","hsn_code":"7304"},"INV-2024-11-0005":{"invoice_id":"INV-2024-11-0005","invoice_number":"INV-2024-11-0005","supplier_gstin":"29RLPTG6380J4ZK","taxable_value":137242.83,"igst_amount":38427.99,"invoice_date":"2024-11-20","hsn_code":"8703"},"INV-2024-11-0006":{"invoice_id":"INV-2024-11-0006","invoice_number":"INV-2024-11-0006","supplier_gstin":"21XLAVT4578L0ZO","taxable_value":102603.06,"igst_amount":0.0,"invoice_date":"2024-11-12","hsn_code":"0301"},"INV-2024-11-0007":{"invoice_id":"INV-2024-11-0007","invoice_number":"INV-2024-11-0007","supplier_gstin":"36SZWBL2332ADZA","taxable_value":34267.57,"igst_amount":0.0,"invoice_date":"2024-11-10","hsn_code":"9999"},"INV-2024-11-0008":{"invoice_id":"INV-2024-11-0008","invoice_number":"INV-2024-11-0008","supplier_gstin":"30CTFID8513W5ZE","taxable_value":43395.49,"igst_amount":7811.19,"invoice_date":"2024-11-13","hsn_code":"9984"},"INV-2024-11-0009":{"invoice_id":"INV-2024-11-0009","invoice_number":"INV-2024-11-0009","supplier_gstin":"17YXYIW9984X3ZI","taxable_value":8092.68,"igst_amount":1456.68,"invoice_date":"2024-11-03","hsn_code":"9997"},"INV-2024-11-0010":{"invoice_id":"INV-2024-11-0010","invoice_number":"INV-2024-11-0010","supplier_gstin":"34NCNHD3279S8ZN","taxable_value":11298.83,"igst_amount":2033.79,"invoice_date":"2024-11-22","hsn_code":"3401"},"INV-2024-11-0011":{"invoice_id":"INV-2024-11-0011","invoice_number":"INV-2024-11-0011","supplier_gstin":"20YSGNF1947S0ZU","taxable_value":53460.43,"igst_amount":9622.88,"invoice_date":"2024-11-20","hsn_code":"8525"},"INV-2024-11-0012":{"invoice_id":"INV-2024-11-0012","invoice_number":"INV-2024-11-0012","supplier_gstin":"29KYGYW0939E5Z0","taxable_value":50961.94,"igst_amount":14269.34,"invoice_date":"2024-11-09","hsn_code":"9201"},"INV-2024-11-0013":{"invoice_id":"INV-2024-11-0013","invoice_number":"INV-2024-11-0013","supplier_gstin":"23VLMRQ4368E4Z0","taxable_value":144995.91,"igst_amount":17399.51,"invoice_date":"2024-11-13","hsn_code":"6301"},"INV-2024-11-0014":{"invoice_id":"INV-2024-11-0014","invoice_number":"INV-2024-11-0014","supplier_gstin":"07RQLUC2178CDZV","taxable_value":74247.84,"igst_amount":13364.61,"invoice_date":"2024-11-03","hsn_code":"4016"},"INV-2024-11-0015":{"invoice_id":"INV-2024-11-0015","invoice_number":"INV-2024-11-0015","supplier_gstin":"34TLJNG3920F2ZW","taxable_value":31021.76,"igst_amount":0.0,"invoice_date":"2024-11-09","hsn_code":"9986"},"INV-2024-11-0016":{"invoice_id":"INV-2024-11-0016","invoice_number":"INV-2024-11-0016","supplier_gstin":"06QYFGT9916G2ZU","taxable_value":11122.37,"igst_amount":0.0,"invoice_date":"2024-11-21","hsn_code":"4407"},"INV-2024-11-0017":{"invoice_id":"INV-2024-11-0017","invoice_number":"INV-2024-11-0017","supplier_gstin":"24ITDBQ7452T9Z2","taxable_value":85401.68,"igst_amount":15372.3,"invoice_date":"2024-11-26","hsn_code":"8544"},"INV-2024-11-0018":{"invoice_id":"INV-2024-11-0018","invoice_number":"INV-2024-11-0018","supplier_gstin":"13RTRND1357F5ZB","taxable_value":145166.09,"igst_amount":7258.3,"invoice_date":"2024-11-05","hsn_code":"0901"},"INV-2024-11-0019":{"invoice_id":"INV-2024-11-0019","invoice_number":"INV-2024-11-0019","supplier_gstin":"34RTPFD7952V5ZF","taxable_value":84815.69,"igst_amount":10177.88,"invoice_date":"2024-11-02","hsn_code":"8601"},"INV-2024-11-0020":{"invoice_id":"INV-2024-11-0020","invoice_number":"INV-2024-11-0020","supplier_gstin":"02FQYUT1627SBZ1","taxable_value":43225.17,"igst_amount":7780.53,"invoice_date":"2024-11-06","hsn_code":"3701"},"INV-2024-11-0021":{"invoice_id":"INV-2024-11-0021","invoice_number":"INV-2024-11-0021","supplier_gstin":"06PRAFT3787R5ZQ","taxable_value":97266.65,"igst_amount":0.0,"invoice_date":"2024-11-10","hsn_code":"0201"},"INV-2024-11-0022":{"invoice_id":"INV-2024-11-0022","invoice_number":"INV-2024-11-0022","supplier_gstin":"01NDHZD6385N3ZA","taxable_value":134173.55,"igst_amount":24151.24,"invoice_date":"2024-11-25","hsn_code":"7001"},"INV-2024-11-0023":{"invoice_id":"INV-2024-11-0023","invoice_number":"INV-2024-11-0023","supplier_gstin":"06WQUPO6841Y8ZB","taxable_value":11800.44,"igst_amount":0.0,"invoice_date":"2024-11-10","hsn_code":"6401"},"INV-2024-11-0024":{"invoice_id":"INV-2024-11-0024","invoice_number":"INV-2024-11-0024","supplier_gstin":"15QGVBT5932T3Z7","taxable_value":100491.17,"igst_amount":28137.53,"invoice_date":"2024-11-07","hsn_code":"2402"},"INV-2024-11-0025":{"invoice_id":"INV-2024-11-0025","invoice_number":"INV-2024-11-0025","supplier_gstin":"18PJZWY2659QBZB","taxable_value":22013.46,"igst_amount":3962.42,"invoice_date":"2024-11-22","hsn_code":"8544"},"INV-2024-11-0026":{"invoice_id":"INV-2024-11-0026","invoice_number":"INV-2024-11-0026","supplier_gstin":"24RPVTE5187T2ZW","taxable_value":129568.15,"igst_amount":23322.27,"invoice_date":"2024-11-02","hsn_code":"8544"},"INV-2024-11-0027":{"invoice_id":"INV-2024-11-0027","invoice_number":"INV-2024-11-0027","supplier_gstin":"27XIPRL4777Q1Z7","taxable_value":158286.24,"igst_amount":0.0,"invoice_date":"2024-11-25","hsn_code":"9999"},"INV-2024-11-0028":{"invoice_id":"INV-2024-11-0028","invoice_number":"INV-2024-11-0028","supplier_gstin":"05LIYCP2777QAZ2","taxable_value":193153.71,"igst_amount":54083.04,"invoice_date":"2024-11-05","hsn_code":"8703"},"INV-2024-11-0029":{"invoice_id":"INV-2024-11-0029","invoice_number":"INV-2024-11-0029","supplier_gstin":"30JUWYB7834BEZK","taxable_value":138033.42,"igst_amount":6901.67,"invoice_date":"2024-11-25","hsn_code":"2804"}},"gstr2b_map":{"2B-00000":{"invoice_id":"2B-00000","invoice_number":"INV-2024-11-0000","supplier_gstin":"04DMJMK9522DEZT","taxable_value":10582.68,"igst_amount":1904.88,"invoice_date":"2024-11-27"},"2B-00001":{"invoice_id":"2B-00001","invoice_number":"INV-2024-11-0001","supplier_gstin":"33AKIAN5398A8ZO","taxable_value":68979.49,"igst_amount":8277.54,"invoice_date":"2024-11-11"},"2B-00002":{},"2B-00003":{"invoice_id":"2B-00003","invoice_number":"INV-2024-11-0003","supplier_gstin":"21BSIVA2380DDZN","taxable_value":110638.78,"igst_amount":30978.86,"invoice_date":"2024-11-14"},"2B-00004":{"invoice_id":"2B-00004","invoice_number":"INV-2024-11-0004","supplier_gstin":"34HMNBZ5870O8Z6","taxable_value":60213.08,"igst_amount":10838.35,"invoice_date":"2024-11-13"},"2B-00005":{"invoice_id":"2B-00005","invoice_number":"INV-2024-11-0005","supplier_gstin":"29RLPTG6380J4ZK","taxable_value":136934.51,"igst_amount":38427.99,"invoice_date":"2024-11-20"},"2B-00006":{"invoice_id":"2B-00006","invoice_number":"INV-2024-11-0006","supplier_gstin":"21XLAVT4578L0ZO","taxable_value":102603.06,"igst_amount":0.0,"invoice_date":"2024-11-12"},"2B-00007":{"invoice_id":"2B-00007","invoice_number":"INV-2024-11-0007","supplier_gstin":"36SZWBL2332ADZA","taxable_value":34267.57,"igst_amount":0.0,"invoice_date":"2024-11-10"},"2B-00008":{"invoice_id":"2B-00008","invoice_number":"INV-2024-11-0008","supplier_gstin":"30CTFID8513W5ZE","taxable_value":43395.49,"igst_amount":7811.19,"invoice_date":"2024-11-13"},"2B-00009":{"invoice_id":"2B-00009","invoice_number":"INV-2024-11-0009","supplier_gstin":"17YXYIW9984X3ZI","taxable_value":8092.68,"igst_amount":1456.68,"invoice_date":"2024-11-03"},"2B-00010":{"invoice_id":"2B-00010","invoice_number":"INV-2024-11-0010","supplier_gstin":"34NCNHD3279S8ZN","taxable_value":11298.83,"igst_amount":2033.79,"invoice_date":"2024-11-22"},"2B-00011":{"invoice_id":"2B-00011","invoice_number":"INV-2024-11-0011","supplier_gstin":"20YSGNF1947S0ZU","taxable_value":52922.18,"igst_amount":9622.88,"invoice_date":"2024-11-20"},"2B-00012":{},"2B-00013":{"invoice_id":"2B-00013","invoice_number":"INV-2024-11-0013","supplier_gstin":"23VLMRQ4368E4Z0","taxable_value":144995.91,"igst_amount":17399.51,"invoice_date":"2024-11-13"},"2B-00014":{"invoice_id":"2B-00014","invoice_number":"INV-2024-11-0014","supplier_gstin":"07RQLUC2178CDZV","taxable_value":74247.84,"igst_amount":13364.61,"invoice_date":"2024-11-03"},"2B-00015":{"invoice_id":"2B-00015","invoice_number":"INV-2024-11-0015","supplier_gstin":"34TLJNG3920F2ZW","taxable_value":31021.76,"igst_amount":0.0,"invoice_date":"2024-11-09"},"2B-00016":{"invoice_id":"2B-00016","invoice_number":"INV-2024-11-0016","supplier_gstin":"06QYFGT9916G2ZU","taxable_value":11122.37,"igst_amount":0.0,"invoice_date":"2024-11-21"},"2B-00017":{"invoice_id":"2B-00017","invoice_number":"INV-2024-11-0017","supplier_gstin":"24ITDBQ7452T9Z2","taxable_value":85401.68,"igst_amount":15372.3,"invoice_date":"2024-11-26"},"2B-00018":{"invoice_id":"2B-00018","invoice_number":"INV-2024-11-0018","supplier_gstin":"13RTRND1357F5ZB","taxable_value":145166.09,"igst_amount":7258.3,"invoice_date":"2024-11-05"},"2B-00019":{"invoice_id":"2B-00019","invoice_number":"INV-2024-11-0019","supplier_gstin":"34RTPFD7952V5ZF","taxable_value":63543.27,"igst_amount":10177.88,"invoice_date":"2024-11-02"},"2B-00020":{"invoice_id":"2B-00020","invoice_number":"INV-2024-11-0020","supplier_gstin":"02FQYUT1627SBZ1","taxable_value":43225.17,"igst_amount":7780.53,"invoice_date":"2024-11-06"},"2B-00021":{"invoice_id":"2B-00021","invoice_number":"INV-2024-11-0021","supplier_gstin":"06PRAFT3787R5ZQ","taxable_value":97266.65,"igst_amount":0.0,"invoice_date":"2024-11-10"},"2B-00022":{},"2B-00023":{"invoice_id":"2B-00023","invoice_number":"INV-2024-11-0023","supplier_gstin":"06WQUPO6841Y8ZB","taxable_value":11800.44,"igst_amount":0.0,"invoice_date":"2024-11-10"},"2B-00024":{"invoice_id":"2B-00024","invoice_number":"INV-2024-11-0024","supplier_gstin":"15QGVBT5932T3Z7","taxable_value":100491.17,"igst_amount":28137.53,"invoice_date":"2024-11-07"},"2B-00025":{"invoice_id":"2B-00025","invoice_number":"INV-2024-11-0025","supplier_gstin":"18PJZWY2659QBZB","taxable_value":22013.46,"igst_amount":3962.42,"invoice_date":"2024-11-22"},"2B-00026":{"invoice_id":"2B-00026","invoice_number":"INV-2024-11-0026","supplier_gstin":"24RPVTE5187T2ZW","taxable_value":129568.15,"igst_amount":23322.27,"invoice_date":"2024-11-02"},"2B-00027":{"invoice_id":"2B-00027","invoice_number":"INV-2024-11-0027","supplier_gstin":"27XIPRL4777Q1Z7","taxable_value":158286.24,"igst_amount":0.0,"invoice_date":"2024-11-25"},"2B-00028":{"invoice_id":"2B-00028","invoice_number":"INV-2024-11-0028","supplier_gstin":"05LIYCP2777QAZ2","taxable_value":193153.71,"igst_amount":54083.04,"invoice_date":"2024-11-05"},"2B-00029":{"invoice_id":"2B-00029","invoice_number":"INV-2024-11-0029","supplier_gstin":"30JUWYB7834BEZK","taxable_value":138033.42,"igst_amount":6901.67,"invoice_date":"2024-11-25"}},"correct_matches":{"INV-2024-11-0000":"2B-00000","INV-2024-11-0001":"2B-00001","INV-2024-11-0003":"2B-00003","INV-2024-11-0004":"2B-00004","INV-2024-11-0005":"2B-00005","INV-2024-11-0006":"2B-00006","INV-2024-11-0007":"2B-00007","INV-2024-11-0008":"2B-00008","INV-2024-11-0009":"2B-00009","INV-2024-11-0010":"2B-00010","INV-2024-11-0011":"2B-00011","INV-2024-11-0013":"2B-00013","INV-2024-11-0014":"2B-00014","INV-2024-11-0015":"2B-00015","INV-2024-11-0016":"2B-00016","INV-2024-11-0017":"2B-00017","INV-2024-11-0018":"2B-00018","INV-2024-11-0019":"2B-00019","INV-2024-11-0020":"2B-00020","INV-2024-11-0021":"2B-00021","INV-2024-11-0023":"2B-00023","INV-2024-11-0024":"2B-00024","INV-2024-11-0025":"2B-00025","INV-2024-11-0026":"2B-00026","INV-2024-11-0027":"2B-00027","INV-2024-11-0028":"2B-00028","INV-2024-11-0029":"2B-00029"},"discrepancy_truth":{"INV-2024-11-0002":{"discrepancy_type":"not_in_2b","correct_action_type":"defer_invoice","recommended_action":"defer"},"INV-2024-11-0005":{"discrepancy_type":"amount_diff","recommended_action":"accept_mismatch"},"INV-2024-11-0011":{"discrepancy_type":"amount_diff","recommended_action":"accept_mismatch"},"INV-2024-11-0012":{"discrepancy_type":"not_in_2b","correct_action_type":"defer_invoice","recommended_action":"defer"},"INV-2024-11-0019":{"discrepancy_type":"amount_diff","recommended_action":"dispute"},"INV-2024-11-0022":{"discrepancy_type":"not_in_2b","correct_action_type":"defer_invoice","recommended_action":"defer"}},"best_match":{"INV-2024-11-0000":"2B-00000","INV-2024-11-0001":"2B-00001","INV-2024-11-0003":"2B-00003","INV-2024-11-0004":"2B-00004","INV-2024-11-0005":"2B-00005","INV-2024-11-0006":"2B-00006","INV-2024-11-0007":"2B-00007","INV-2024-11-0008":"2B-00008","INV-2024-11-0009":"2B-00009","INV-2024-11-0010":"2B-00010","INV-2024-11-0011":"2B-00011","INV-2024-11-0013":"2B-00013","INV-2024-11-0014":"2B-00014","INV-2024-11-0015":"2B-00015","INV-2024-11-0016":"2B-00016","INV-2024-11-0017":"2B-00017","INV-2024-11-0018":"2B-00018","INV-2024-11-0019":"2B-00019","INV-2024-11-0020":"2B-00020","INV-2024-11-0021":"2B-00021","INV-2024-11-0023":"2B-00023","INV-2024-11-0024":"2B-00024","INV-2024-11-0025":"2B-00025","INV-2024-11-0026":"2B-00026","INV-2024-11-0027":"2B-00027","INV-2024-11-0028":"2B-00028","INV-2024-11-0029":"2B-00029"},"mismatches":[{"purchase_invoice_id":"INV-2024-11-0002","gstr2b_invoice_id":null,"mismatch_type":"not_in_2b","purchase_taxable":63295.28,"gstr2b_taxable":null,"delta":63295.28},{"purchase_invoice_id":"INV-2024-11-0005","gstr2b_invoice_id":"2B-00005","mismatch_type":"amount_diff","purchase_taxable":137242.83,"gstr2b_taxable":136934.51,"delta":308.32},{"purchase_invoice_id":"INV-2024-11-0011","gstr2b_invoice_id":"2B-00011","mismatch_type":"amount_diff","purchase_taxable":53460.43,"gstr2b_taxable":52922.18,"delta":538.25},{"purchase_invoice_id":"INV-2024-11-0012","gstr2b_invoice_id":null,"mismatch_type":"not_in_2b","purchase_taxable":50961.94,"gstr2b_taxable":null,"delta":50961.94},{"purchase_invoice_id":"INV-2024-11-0019","gstr2b_invoice_id":"2B-00019","mismatch_type":"amount_diff","purchase_taxable":84815.69,"gstr2b_taxable":63543.27,"delta":21272.42},{"purchase_invoice_id":"INV-2024-11-0022","gstr2b_invoice_id":null,"mismatch_type":"not_in_2b","purchase_taxable":134173.55,"gstr2b_taxable":null,"delta":134173.55}],"ground_truth":{"INV-2024-11-0000":{"invoice_id":"INV-2024-11-0000","invoice_type":"B2B","hsn_code":"9995","gst_slab":"18","supply_type":"services","itc_eligible":true,"reverse_charge":false},"INV-2024-11-0001":{"invoice_id":"INV-2024-11-0001","invoice_type":"EXPORT","hsn_code":"6601","gst_slab":"12","supply_type":"goods","itc_eligible":false,"reverse_charge":false},"INV-2024-11-0002":{"invoice_id":"INV-2024-11-0002","invoice_type":"B2B","hsn_code":"9984","gst_slab":"18","supply_type":"services","itc_eligible":true,"reverse_charge":false},"INV-2024-11-0003":{"invoice_id":"INV-2024-11-0003","invoice_type":"B2B","hsn_code":"9201","gst_slab":"28","supply_type":"goods","itc_eligible":true,"reverse_charge":false},"INV-2024-11-0004":{"invoice_id":"INV-2024-11-0004","invoice_type":"EXPORT","hsn_code":"7304","gst_slab":"18","supply_type":"goods","itc_eligible":false,"reverse_charge":false},"INV-2024-11-0005":{"invoice_id":"INV-2024-11-0005","invoice_type":"B2C","hsn_code":"8703","gst_slab":"28","supply_type":"goods","itc_eligible":false,"reverse_charge":false},"INV-2024-11-0006":{"invoice_id":"INV-2024-11-0006","invoice_type":"B2B","hsn_code":"0301","gst_slab":"0","supply_type":"goods","itc_eligible":true,"reverse_charge":false},"INV-2024-11-0007":{"invoice_id":"INV-2024-11-0007","invoice_type":"B2B","hsn_code":"9999","gst_slab":"0","supply_type":"services","itc_eligible":true,"reverse_charge":false},"INV-2024-11-0008":{"invoice_id":"INV-2024-11-0008","invoice_type":"B2B","hsn_code":"9984","gst_slab":"18","supply_type":"services","itc_eligible":true,"reverse_charge":false},"INV-2024-11-0009":{"invoice_id":"INV-2024-11-0009","invoice_type":"B2B","hsn_code":"9997","gst_slab":"18","supply_type":"services","itc_eligible":true,"reverse_charge":false},"INV-2024-11-0010":{"invoice_id":"INV-2024-11-0010","invoice_type":"B2B","hsn_code":"3401","gst_slab":"18","supply_type":"goods","itc_eligible":true,"reverse_charge":false},"INV-2024-11-0011":{"invoice_id":"INV-2024-11-0011","invoice_type":"B2B","hsn_code":"8525","gst_slab":"18","supply_type":"goods","itc_eligible":true,"reverse_charge":false},"INV-2024-11-0012":{"invoice_id":"INV-2024-11-0012","invoice_type":"RCM","hsn_code":"9201","gst_slab":"28","supply_type":"goods","itc_eligible":true,"reverse_charge":true},"INV-2024-11-0013":{"invoice_id":"INV-2024-11-0013","invoice_type":"B2C","hsn_code":"6301","gst_slab":"12","supply_type":"goods","itc_eligible":false,"reverse_charge":false},"INV-2024-11-0014":{"invoice_id":"INV-2024-11-0014","invoice_type":"B2C","hsn_code":"4016","gst_slab":"18","supply_type":"goods","itc_eligible":false,"reverse_charge":false},"INV-2024-11-0015":{"invoice_id":"INV-2024-11-0015","invoice_type":"B2C","hsn_code":"9986","gst_slab":"0","supply_type":"services","itc_eligible":false,"reverse_charge":false},"INV-2024-11-0016":{"invoice_id":"INV-2024-11-0016","invoice_type":"B2B","hsn_code":"4407","gst_slab":"12","supply_type":"goods","itc_eligible":true,"reverse_charge":false},"INV-2024-11-0017":{"invoice_id":"INV-2024-11-0017","invoice_type":"B2B","hsn_code":"8544","gst_slab":"18","supply_type":"goods","itc_eligible":true,"reverse_charge":false},"INV-2024-11-0018":{"invoice_id":"INV-2024-11-0018","invoice_type":"B2B","hsn_code":"0901","gst_slab":"5","supply_type":"goods","itc_eligible":true,"reverse_charge":false},"INV-2024-11-0019":{"invoice_id":"INV-2024-11-0019","invoice_type":"B2B","hsn_code":"8601","gst_slab":"12","supply_type":"goods","itc_eligible":true,"reverse_charge":false},"INV-2024-11-0020":{"invoice_id":"INV-2024-11-0020","invoice_type":"B2C","hsn_code":"3701","gst_slab":"18","supply_type":"goods","itc_eligible":false,"reverse_charge":false},"INV-2024-11-0021":{"invoice_id":"INV-2024-11-0021","invoice_type":"B2B","hsn_code":"0201","gst_slab":"0","supply_type":"goods","itc_eligible":true,"reverse_charge":false},"INV-2024-11-0022":{"invoice_id":"INV-2024-11-0022","invoice_type":"B2B","hsn_code":"7001","gst_slab":"18","supply_type":"goods","itc_eligible":true,"reverse_charge":false},"INV-2024-11-0023":{"invoice_id":"INV-2024-11-0023","invoice_type":"B2B","hsn_code":"6401","gst_slab":"18","supply_type":"goods","itc_eligible":true,"reverse_charge":false},"INV-2024-11-0024":{"invoice_id":"INV-2024-11-0024","invoice_type":"EXPORT","hsn_code":"2402","gst_slab":"28","supply_type":"goods","itc_eligible":false,"reverse_charge":false},"INV-2024-11-0025":{"invoice_id":"INV-2024-11-0025","invoice_type":"B2B","hsn_code":"8544","gst_slab":"18","supply_type":"goods","itc_eligible":true,"reverse_charge":false},"INV-2024-11-0026":{"invoice_id":"INV-2024-11-0026","invoice_type":"B2C","hsn_code":"8544","gst_slab":"18","supply_type":"goods","itc_eligible":false,"reverse_charge":false},"INV-2024-11-0027":{"invoice_id":"INV-2024-11-0027","invoice_type":"B2B","hsn_code":"9999","gst_slab":"0","supply_type":"services","itc_eligible":true,"reverse_charge":false},"INV-2024-11-0028":{"invoice_id":"INV-2024-11-0028","invoice_type":"B2B","hsn_code":"8703","gst_slab":"28","supply_type":"goods","itc_eligible":true,"reverse_charge":false},"INV-2024-11-0029":{"invoice_id":"INV-2024-11-0029","invoice_type":"B2B","hsn_code":"2804","gst_slab":"5","supply_type":"goods","itc_eligible":true,"reverse_charge":false}},"supplier_profiles":{"04DMJMK9522DEZT":{"compliance_rate":0.9014,"avg_delay_days":13.6,"cancelled_pct":0.0438},"33AKIAN5398A8ZO":{"compliance_rate":0.8703,"avg_delay_days":5.1,"cancelled_pct":0.0154},"21UNCLS1753F9ZN":{"compliance_rate":0.8891,"avg_delay_days":1.1,"cancelled_pct":0.0235},"21BSIVA2380DDZN":{"compliance_rate":0.8875,"avg_delay_days":8.6,"cancelled_pct":0.0238},"34HMNBZ5870O8Z6":{"compliance_rate":0.9743,"avg_delay_days":13.9,"cancelled_pct":0.0393},"29RLPTG6380J4ZK":{"compliance_rate":0.9061,"avg_delay_days":4.3,"cancelled_pct":0.0209},"21XLAVT4578L0ZO":{"compliance_rate":0.9301,"avg_delay_days":1.8,"cancelled_pct":0.0007},"36SZWBL2332ADZA":{"compliance_rate":0.8383,"avg_delay_days":1.7,"cancelled_pct":0.0101},"30CTFID8513W5ZE":{"compliance_rate":0.9546,"avg_delay_days":10.2,"cancelled_pct":0.0153},"17YXYIW9984X3ZI":{"compliance_rate":0.881,"avg_delay_days":10.7,"cancelled_pct":0.0313},"34NCNHD3279S8ZN":{"compliance_rate":0.8569,"avg_delay_days":7.9,"cancelled_pct":0.0339},"20YSGNF1947S0ZU":{"compliance_rate":0.8456,"avg_delay_days":10.4,"cancelled_pct":0.0233},"29KYGYW0939E5Z0":{"compliance_rate":0.9087,"avg_delay_days":5.5,"cancelled_pct":0.0449},"23VLMRQ4368E4Z0":{"compliance_rate":0.8432,"avg_delay_days":5.9,"cancelled_pct":0.0367},"07RQLUC2178CDZV":{"compliance_rate":0.9997,"avg_delay_days":3.4,"cancelled_pct":0.0077},"34TLJNG3920F2ZW":{"compliance_rate":0.9382,"avg_delay_days":1.0,"cancelled_pct":0.0377},"06QYFGT9916G2ZU":{"compliance_rate":0.9294,"avg_delay_days":7.6,"cancelled_pct":0.0377},"24ITDBQ7452T9Z2":{"compliance_rate":0.9637,"avg_delay_days":4.6,"cancelled_pct":0.016},"13RTRND1357F5ZB":{"compliance_rate":0.982,"avg_delay_days":0.7,"cancelled_pct":0.0095},"34RTPFD7952V5ZF":{"compliance_rate":0.8791,"avg_delay_days":2.8,"cancelled_pct":0.0064},"02FQYUT1627SBZ1":{"compliance_rate":0.8857,"avg_delay_days":13.9,"cancelled_pct":0.0243},"06PRAFT3787R5ZQ":{"compliance_rate":0.9884,"avg_delay_days":8.8,"cancelled_pct":0.0083},"01NDHZD6385N3ZA":{"compliance_rate":0.8712,"avg_delay_days":9.4,"cancelled_pct":0.025},"06WQUPO6841Y8ZB":{"compliance_rate":0.8453,"avg_delay_days":13.7,"cancelled_pct":0.006},"15QGVBT5932T3Z7":{"compliance_rate":0.835,"avg_delay_days":6.1,"cancelled_pct":0.0153},"18PJZWY2659QBZB":{"compliance_rate":0.9276,"avg_delay_days":13.8,"cancelled_pct":0.0043},"24RPVTE5187T2ZW":{"compliance_rate":0.9324,"avg_delay_days":0.9,"cancelled_pct":0.0038},"27XIPRL4777Q1Z7":{"compliance_rate":0.8138,"avg_delay_days":11.5,"cancelled_pct":0.0134},"05LIYCP2777QAZ2":{"compliance_rate":0.9662,"avg_delay_days":9.2,"cancelled_pct":0.003},"30JUWYB7834BEZK":{"compliance_rate":0.9783,"avg_delay_days":5.1,"cancelled_pct":0.025}},"eligible_itc":352384.71}}