{"episode_idx":178,"task_id":2,"seed":220,"split":"train","batch":{"gstin":"24TSLSK2341L7ZO","tax_period":"2023-01","invoices":[{"invoice_id":"INV-2023-01-0000","supplier_gstin":"03FSNHI0797HCZG","buyer_gstin":"24TSLSK2341L7ZO","invoice_date":"2023-01-24","invoice_type":"B2B","hsn_code":"9954","description":"Construction Services","taxable_value":173361.1,"igst_amount":31205.0,"cgst_amount":0.0,"sgst_amount":0.0,"total_amount":204566.1,"gstr2b_match":null,"status":"pending","flags":[]},{"invoice_id":"INV-2023-01-0001","supplier_gstin":"19VNEAW9059T8ZG","buyer_gstin":"24TSLSK2341L7ZO","invoice_date":"2023-01-14","invoice_type":"B2B","hsn_code":"6601","description":"Umbrellas","taxable_value":21146.22,"igst_amount":2537.55,"cgst_amount":0.0,"sgst_amount":0.0,"total_amount":23683.77,"gstr2b_match":null,"status":"pending","flags":[]},{"invoice_id":"INV-2023-01-0002","supplier_gstin":"21TPHNP5763CDZ6","buyer_gstin":"24TSLSK2341L7ZO","invoice_date":"2023-01-24","invoice_type":"B2B","hsn_code":"9983","description":"IT and Computer Services","taxable_value":36756.51,"igst_amount":6616.17,"cgst_amount":0.0,"sgst_amount":0.0,"total_amount":43372.68,"gstr2b_match":null,"status":"pending","flags":[]},{"invoice_id":"INV-2023-01-0003","supplier_gstin":"02WFCGP2863E5ZG","buyer_gstin":"24TSLSK2341L7ZO","invoice_date":"2023-01-12","invoice_type":"B2B","hsn_code":"9971","description":"Financial and Related Services","taxable_value":20464.77,"igst_amount":3683.66,"cgst_amount":0.0,"sgst_amount":0.0,"total_amount":24148.43,"gstr2b_match":null,"status":"pending","flags":[]},{"invoice_id":"INV-2023-01-0004","supplier_gstin":"34POWGH3913A3Z3","buyer_gstin":"24TSLSK2341L7ZO","invoice_date":"2023-01-23","invoice_type":"B2C","hsn_code":"6601","description":"Umbrellas","taxable_value":56395.73,"igst_amount":6767.49,"cgst_amount":0.0,"sgst_amount":0.0,"total_amount":63163.22,"gstr2b_match":null,"status":"pending","flags":[]},{"invoice_id":"INV-2023-01-0005","supplier_gstin":"29BQXFE3727QEZV","buyer_gstin":"24TSLSK2341L7ZO","invoice_date":"2023-01-25","invoice_type":"B2B","hsn_code":"8703","description":"Motor Cars","taxable_value":32725.71,"igst_amount":9163.2,"cgst_amount":0.0,"sgst_amount":0.0,"total_amount":41888.91,"gstr2b_match":null,"status":"pending","flags":[]},{"invoice_id":"INV-2023-01-0006","supplier_gstin":"16HCCQP1110K9ZE","buyer_gstin":"24TSLSK2341L7ZO","invoice_date":"2023-01-22","invoice_type":"B2B","hsn_code":"9988","description":"Manufacturing Services","taxable_value":133475.6,"igst_amount":24025.61,"cgst_amount":0.0,"sgst_amount":0.0,"total_amount":157501.21,"gstr2b_match":null,"status":"pending","flags":[]},{"invoice_id":"INV-2023-01-0007","supplier_gstin":"08WKAIR5223A4Z7","buyer_gstin":"24TSLSK2341L7ZO","invoice_date":"2023-01-09","invoice_type":"RCM","hsn_code":"9997","description":"Other Personal Services","taxable_value":90367.34,"igst_amount":16266.12,"cgst_amount":0.0,"sgst_amount":0.0,"total_amount":106633.46,"gstr2b_match":null,"status":"pending","flags":[]},{"invoice_id":"INV-2023-01-0008","supplier_gstin":"12VBXSS2431L5Z9","buyer_gstin":"24TSLSK2341L7ZO","invoice_date":"2023-01-22","invoice_type":"B2B","hsn_code":"3605","description":"Safety Matches","taxable_value":48784.4,"igst_amount":5854.13,"cgst_amount":0.0,"sgst_amount":0.0,"total_amount":54638.53,"gstr2b_match":null,"status":"pending","flags":[]},{"invoice_id":"INV-2023-01-0009","supplier_gstin":"34GSACS3481WDZW","buyer_gstin":"24TSLSK2341L7ZO","invoice_date":"2023-01-14","invoice_type":"B2C","hsn_code":"6401","description":"Waterproof Footwear","taxable_value":61695.73,"igst_amount":11105.23,"cgst_amount":0.0,"sgst_amount":0.0,"total_amount":72800.96,"gstr2b_match":null,"status":"pending","flags":[]},{"invoice_id":"INV-2023-01-0010","supplier_gstin":"32OQUOJ3472JBZQ","buyer_gstin":"24TSLSK2341L7ZO","invoice_date":"2023-01-09","invoice_type":"B2B","hsn_code":"7101","description":"Pearls, Natural or Cultured","taxable_value":97474.71,"igst_amount":0.0,"cgst_amount":0.0,"sgst_amount":0.0,"total_amount":97474.71,"gstr2b_match":null,"status":"pending","flags":[]},{"invoice_id":"INV-2023-01-0011","supplier_gstin":"04ZDMSM7159CEZ5","buyer_gstin":"24TSLSK2341L7ZO","invoice_date":"2023-01-12","invoice_type":"B2C","hsn_code":"6401","description":"Waterproof Footwear","taxable_value":83315.61,"igst_amount":14996.81,"cgst_amount":0.0,"sgst_amount":0.0,"total_amount":98312.42,"gstr2b_match":null,"status":"pending","flags":[]},{"invoice_id":"INV-2023-01-0012","supplier_gstin":"21CLCML6402NBZ1","buyer_gstin":"24TSLSK2341L7ZO","invoice_date":"2023-01-23","invoice_type":"B2B","hsn_code":"7407","description":"Copper Bars and Rods","taxable_value":94873.0,"igst_amount":17077.14,"cgst_amount":0.0,"sgst_amount":0.0,"total_amount":111950.14,"gstr2b_match":null,"status":"pending","flags":[]},{"invoice_id":"INV-2023-01-0013","supplier_gstin":"19TRWFG0259J8ZY","buyer_gstin":"24TSLSK2341L7ZO","invoice_date":"2023-01-08","invoice_type":"EXPORT","hsn_code":"8544","description":"Insulated Wire and Cable","taxable_value":75816.4,"igst_amount":13646.95,"cgst_amount":0.0,"sgst_amount":0.0,"total_amount":89463.35,"gstr2b_match":null,"status":"pending","flags":[]},{"invoice_id":"INV-2023-01-0014","supplier_gstin":"29JVKNU8587K6ZT","buyer_gstin":"24TSLSK2341L7ZO","invoice_date":"2023-01-14","invoice_type":"B2C","hsn_code":"8443","description":"Printing Machinery","taxable_value":133199.71,"igst_amount":23975.95,"cgst_amount":0.0,"sgst_amount":0.0,"total_amount":157175.66,"gstr2b_match":null,"status":"pending","flags":[]},{"invoice_id":"INV-2023-01-0015","supplier_gstin":"33RBDDD1757Y6Z1","buyer_gstin":"24TSLSK2341L7ZO","invoice_date":"2023-01-19","invoice_type":"B2B","hsn_code":"9981","description":"R&D Services","taxable_value":156849.6,"igst_amount":28232.93,"cgst_amount":0.0,"sgst_amount":0.0,"total_amount":185082.53,"gstr2b_match":null,"status":"pending","flags":[]},{"invoice_id":"INV-2023-01-0016","supplier_gstin":"33ZMMML1999O7ZD","buyer_gstin":"24TSLSK2341L7ZO","invoice_date":"2023-01-06","invoice_type":"B2B","hsn_code":"8443","description":"Printing Machinery","taxable_value":122786.58,"igst_amount":22101.58,"cgst_amount":0.0,"sgst_amount":0.0,"total_amount":144888.16,"gstr2b_match":null,"status":"pending","flags":[]},{"invoice_id":"INV-2023-01-0017","supplier_gstin":"09URHLL5579O4Z9","buyer_gstin":"24TSLSK2341L7ZO","invoice_date":"2023-01-22","invoice_type":"B2C","hsn_code":"4901","description":"Printed Books, Brochures","taxable_value":183689.32,"igst_amount":0.0,"cgst_amount":0.0,"sgst_amount":0.0,"total_amount":183689.32,"gstr2b_match":null,"status":"pending","flags":[]},{"invoice_id":"INV-2023-01-0018","supplier_gstin":"10QUXMR9263U0ZU","buyer_gstin":"24TSLSK2341L7ZO","invoice_date":"2023-01-01","invoice_type":"B2C","hsn_code":"6109","description":"T-Shirts and Singlets","taxable_value":40155.42,"igst_amount":2007.77,"cgst_amount":0.0,"sgst_amount":0.0,"total_amount":42163.19,"gstr2b_match":null,"status":"pending","flags":[]},{"invoice_id":"INV-2023-01-0019","supplier_gstin":"08HCNAH3156C0ZC","buyer_gstin":"24TSLSK2341L7ZO","invoice_date":"2023-01-04","invoice_type":"EXPORT","hsn_code":"3401","description":"Soap","taxable_value":95055.3,"igst_amount":17109.95,"cgst_amount":0.0,"sgst_amount":0.0,"total_amount":112165.25,"gstr2b_match":null,"status":"pending","flags":[]},{"invoice_id":"INV-2023-01-0020","supplier_gstin":"04VTHVR7020REZR","buyer_gstin":"24TSLSK2341L7ZO","invoice_date":"2023-01-20","invoice_type":"B2C","hsn_code":"8601","description":"Rail Locomotives","taxable_value":103879.56,"igst_amount":12465.55,"cgst_amount":0.0,"sgst_amount":0.0,"total_amount":116345.11,"gstr2b_match":null,"status":"pending","flags":[]},{"invoice_id":"INV-2023-01-0021","supplier_gstin":"19GUXPY7021M7ZY","buyer_gstin":"24TSLSK2341L7ZO","invoice_date":"2023-01-16","invoice_type":"B2C","hsn_code":"2101","description":"Extracts of Coffee","taxable_value":129983.67,"igst_amount":23397.06,"cgst_amount":0.0,"sgst_amount":0.0,"total_amount":153380.73,"gstr2b_match":null,"status":"pending","flags":[]},{"invoice_id":"INV-2023-01-0022","supplier_gstin":"34GQSAS2374A7Z4","buyer_gstin":"24TSLSK2341L7ZO","invoice_date":"2023-01-27","invoice_type":"B2B","hsn_code":"9701","description":"Paintings and Drawings","taxable_value":11837.74,"igst_amount":1420.53,"cgst_amount":0.0,"sgst_amount":0.0,"total_amount":13258.27,"gstr2b_match":null,"status":"pending","flags":[]},{"invoice_id":"INV-2023-01-0023","supplier_gstin":"14CHSOG4664I0ZX","buyer_gstin":"24TSLSK2341L7ZO","invoice_date":"2023-01-07","invoice_type":"B2C","hsn_code":"9984","description":"Telecommunications Services","taxable_value":19369.12,"igst_amount":3486.44,"cgst_amount":0.0,"sgst_amount":0.0,"total_amount":22855.56,"gstr2b_match":null,"status":"pending","flags":[]},{"invoice_id":"INV-2023-01-0024","supplier_gstin":"03NUITR6302QBZ9","buyer_gstin":"24TSLSK2341L7ZO","invoice_date":"2023-01-13","invoice_type":"RCM","hsn_code":"4016","description":"Articles of Rubber","taxable_value":196763.76,"igst_amount":35417.48,"cgst_amount":0.0,"sgst_amount":0.0,"total_amount":232181.24,"gstr2b_match":null,"status":"pending","flags":[]},{"invoice_id":"INV-2023-01-0025","supplier_gstin":"29LPNJK2626O8ZX","buyer_gstin":"24TSLSK2341L7ZO","invoice_date":"2023-01-08","invoice_type":"B2B","hsn_code":"3102","description":"Nitrogenous Fertilisers","taxable_value":96973.95,"igst_amount":4848.7,"cgst_amount":0.0,"sgst_amount":0.0,"total_amount":101822.65,"gstr2b_match":null,"status":"pending","flags":[]},{"invoice_id":"INV-2023-01-0026","supplier_gstin":"05PPDFL9561L3ZG","buyer_gstin":"24TSLSK2341L7ZO","invoice_date":"2023-01-23","invoice_type":"B2B","hsn_code":"9993","description":"Human Health Services","taxable_value":132473.6,"igst_amount":0.0,"cgst_amount":0.0,"sgst_amount":0.0,"total_amount":132473.6,"gstr2b_match":null,"status":"pending","flags":[]},{"invoice_id":"INV-2023-01-0027","supplier_gstin":"13GLGTE6203EDZ0","buyer_gstin":"24TSLSK2341L7ZO","invoice_date":"2023-01-16","invoice_type":"B2B","hsn_code":"0101","description":"Live Horses and Asses","taxable_value":80315.12,"igst_amount":0.0,"cgst_amount":0.0,"sgst_amount":0.0,"total_amount":80315.12,"gstr2b_match":null,"status":"pending","flags":[]},{"invoice_id":"INV-2023-01-0028","supplier_gstin":"02DRCVN4902L2ZF","buyer_gstin":"24TSLSK2341L7ZO","invoice_date":"2023-01-28","invoice_type":"B2B","hsn_code":"9954","description":"Construction Services","taxable_value":141336.18,"igst_amount":25440.51,"cgst_amount":0.0,"sgst_amount":0.0,"total_amount":166776.69,"gstr2b_match":null,"status":"pending","flags":[]},{"invoice_id":"INV-2023-01-0029","supplier_gstin":"15WQXIA7683QEZ2","buyer_gstin":"24TSLSK2341L7ZO","invoice_date":"2023-01-05","invoice_type":"B2B","hsn_code":"8601","description":"Rail Locomotives","taxable_value":130948.79,"igst_amount":15713.85,"cgst_amount":0.0,"sgst_amount":0.0,"total_amount":146662.64,"gstr2b_match":null,"status":"pending","flags":[]}],"purchase_map":{"INV-2023-01-0000":{"invoice_id":"INV-2023-01-0000","invoice_number":"INV-2023-01-0000","supplier_gstin":"03FSNHI0797HCZG","taxable_value":173361.1,"igst_amount":31205.0,"invoice_date":"2023-01-24","hsn_code":"9954"},"INV-2023-01-0001":{"invoice_id":"INV-2023-01-0001","invoice_number":"INV-2023-01-0001","supplier_gstin":"19VNEAW9059T8ZG","taxable_value":21146.22,"igst_amount":2537.55,"invoice_date":"2023-01-14","hsn_code":"6601"},"INV-2023-01-0002":{"invoice_id":"INV-2023-01-0002","invoice_number":"INV-2023-01-0002","supplier_gstin":"21TPHNP5763CDZ6","taxable_value":36756.51,"igst_amount":6616.17,"invoice_date":"2023-01-24","hsn_code":"9983"},"INV-2023-01-0003":{"invoice_id":"INV-2023-01-0003","invoice_number":"INV-2023-01-0003","supplier_gstin":"02WFCGP2863E5ZG","taxable_value":20464.77,"igst_amount":3683.66,"invoice_date":"2023-01-12","hsn_code":"9971"},"INV-2023-01-0004":{"invoice_id":"INV-2023-01-0004","invoice_number":"INV-2023-01-0004","supplier_gstin":"34POWGH3913A3Z3","taxable_value":56395.73,"igst_amount":6767.49,"invoice_date":"2023-01-23","hsn_code":"6601"},"INV-2023-01-0005":{"invoice_id":"INV-2023-01-0005","invoice_number":"INV-2023-01-0005","supplier_gstin":"29BQXFE3727QEZV","taxable_value":32725.71,"igst_amount":9163.2,"invoice_date":"2023-01-25","hsn_code":"8703"},"INV-2023-01-0006":{"invoice_id":"INV-2023-01-0006","invoice_number":"INV-2023-01-0006","supplier_gstin":"16HCCQP1110K9ZE","taxable_value":133475.6,"igst_amount":24025.61,"invoice_date":"2023-01-22","hsn_code":"9988"},"INV-2023-01-0007":{"invoice_id":"INV-2023-01-0007","invoice_number":"INV-2023-01-0007","supplier_gstin":"08WKAIR5223A4Z7","taxable_value":90367.34,"igst_amount":16266.12,"invoice_date":"2023-01-09","hsn_code":"9997"},"INV-2023-01-0008":{"invoice_id":"INV-2023-01-0008","invoice_number":"INV-2023-01-0008","supplier_gstin":"12VBXSS2431L5Z9","taxable_value":48784.4,"igst_amount":5854.13,"invoice_date":"2023-01-22","hsn_code":"3605"},"INV-2023-01-0009":{"invoice_id":"INV-2023-01-0009","invoice_number":"INV-2023-01-0009","supplier_gstin":"34GSACS3481WDZW","taxable_value":61695.73,"igst_amount":11105.23,"invoice_date":"2023-01-14","hsn_code":"6401"},"INV-2023-01-0010":{"invoice_id":"INV-2023-01-0010","invoice_number":"INV-2023-01-0010","supplier_gstin":"32OQUOJ3472JBZQ","taxable_value":97474.71,"igst_amount":0.0,"invoice_date":"2023-01-09","hsn_code":"7101"},"INV-2023-01-0011":{"invoice_id":"INV-2023-01-0011","invoice_number":"INV-2023-01-0011","supplier_gstin":"04ZDMSM7159CEZ5","taxable_value":83315.61,"igst_amount":14996.81,"invoice_date":"2023-01-12","hsn_code":"6401"},"INV-2023-01-0012":{"invoice_id":"INV-2023-01-0012","invoice_number":"INV-2023-01-0012","supplier_gstin":"21CLCML6402NBZ1","taxable_value":94873.0,"igst_amount":17077.14,"invoice_date":"2023-01-23","hsn_code":"7407"},"INV-2023-01-0013":{"invoice_id":"INV-2023-01-0013","invoice_number":"INV-2023-01-0013","supplier_gstin":"19TRWFG0259J8ZY","taxable_value":75816.4,"igst_amount":13646.95,"invoice_date":"2023-01-08","hsn_code":"8544"},"INV-2023-01-0014":{"invoice_id":"INV-2023-01-0014","invoice_number":"INV-2023-01-0014","supplier_gstin":"29JVKNU8587K6ZT","taxable_value":133199.71,"igst_amount":23975.95,"invoice_date":"2023-01-14","hsn_code":"8443"},"INV-2023-01-0015":{"invoice_id":"INV-2023-01-0015","invoice_number":"INV-2023-01-0015","supplier_gstin":"33RBDDD1757Y6Z1","taxable_value":156849.6,"igst_amount":28232.93,"invoice_date":"2023-01-19","hsn_code":"9981"},"INV-2023-01-0016":{"invoice_id":"INV-2023-01-0016","invoice_number":"INV-2023-01-0016","supplier_gstin":"33ZMMML1999O7ZD","taxable_value":122786.58,"igst_amount":22101.58,"invoice_date":"2023-01-06","hsn_code":"8443"},"INV-2023-01-0017":{"invoice_id":"INV-2023-01-0017","invoice_number":"INV-2023-01-0017","supplier_gstin":"09URHLL5579O4Z9","taxable_value":183689.32,"igst_amount":0.0,"invoice_date":"2023-01-22","hsn_code":"4901"},"INV-2023-01-0018":{"invoice_id":"INV-2023-01-0018","invoice_number":"INV-2023-01-0018","supplier_gstin":"10QUXMR9263U0ZU","taxable_value":40155.42,"igst_amount":2007.77,"invoice_date":"2023-01-01","hsn_code":"6109"},"INV-2023-01-0019":{"invoice_id":"INV-2023-01-0019","invoice_number":"INV-2023-01-0019","supplier_gstin":"08HCNAH3156C0ZC","taxable_value":95055.3,"igst_amount":17109.95,"invoice_date":"2023-01-04","hsn_code":"3401"},"INV-2023-01-0020":{"invoice_id":"INV-2023-01-0020","invoice_number":"INV-2023-01-0020","supplier_gstin":"04VTHVR7020REZR","taxable_value":103879.56,"igst_amount":12465.55,"invoice_date":"2023-01-20","hsn_code":"8601"},"INV-2023-01-0021":{"invoice_id":"INV-2023-01-0021","invoice_number":"INV-2023-01-0021","supplier_gstin":"19GUXPY7021M7ZY","taxable_value":129983.67,"igst_amount":23397.06,"invoice_date":"2023-01-16","hsn_code":"2101"},"INV-2023-01-0022":{"invoice_id":"INV-2023-01-0022","invoice_number":"INV-2023-01-0022","supplier_gstin":"34GQSAS2374A7Z4","taxable_value":11837.74,"igst_amount":1420.53,"invoice_date":"2023-01-27","hsn_code":"9701"},"INV-2023-01-0023":{"invoice_id":"INV-2023-01-0023","invoice_number":"INV-2023-01-0023","supplier_gstin":"14CHSOG4664I0ZX","taxable_value":19369.12,"igst_amount":3486.44,"invoice_date":"2023-01-07","hsn_code":"9984"},"INV-2023-01-0024":{"invoice_id":"INV-2023-01-0024","invoice_number":"INV-2023-01-0024","supplier_gstin":"03NUITR6302QBZ9","taxable_value":196763.76,"igst_amount":35417.48,"invoice_date":"2023-01-13","hsn_code":"4016"},"INV-2023-01-0025":{"invoice_id":"INV-2023-01-0025","invoice_number":"INV-2023-01-0025","supplier_gstin":"29LPNJK2626O8ZX","taxable_value":96973.95,"igst_amount":4848.7,"invoice_date":"2023-01-08","hsn_code":"3102"},"INV-2023-01-0026":{"invoice_id":"INV-2023-01-0026","invoice_number":"INV-2023-01-0026","supplier_gstin":"05PPDFL9561L3ZG","taxable_value":132473.6,"igst_amount":0.0,"invoice_date":"2023-01-23","hsn_code":"9993"},"INV-2023-01-0027":{"invoice_id":"INV-2023-01-0027","invoice_number":"INV-2023-01-0027","supplier_gstin":"13GLGTE6203EDZ0","taxable_value":80315.12,"igst_amount":0.0,"invoice_date":"2023-01-16","hsn_code":"0101"},"INV-2023-01-0028":{"invoice_id":"INV-2023-01-0028","invoice_number":"INV-2023-01-0028","supplier_gstin":"02DRCVN4902L2ZF","taxable_value":141336.18,"igst_amount":25440.51,"invoice_date":"2023-01-28","hsn_code":"9954"},"INV-2023-01-0029":{"invoice_id":"INV-2023-01-0029","invoice_number":"INV-2023-01-0029","supplier_gstin":"15WQXIA7683QEZ2","taxable_value":130948.79,"igst_amount":15713.85,"invoice_date":"2023-01-05","hsn_code":"8601"}},"gstr2b_map":{"2B-00000":{"invoice_id":"2B-00000","invoice_number":"INV-2023-01-0000","supplier_gstin":"03FSNHI0797HCZG","taxable_value":173361.1,"igst_amount":31205.0,"invoice_date":"2023-01-24"},"2B-00001":{"invoice_id":"2B-00001","invoice_number":"INV-2023-01-0001","supplier_gstin":"19VNEAW9059T8ZG","taxable_value":-483.72,"igst_amount":2537.55,"invoice_date":"2023-01-14"},"2B-00002":{"invoice_id":"2B-00002","invoice_number":"INV-2023-01-0002","supplier_gstin":"21TPHNP5763CDZ6","taxable_value":36756.51,"igst_amount":6616.17,"invoice_date":"2023-01-24"},"2B-00003":{"invoice_id":"2B-00003","invoice_number":"INV-2023-01-0003","supplier_gstin":"02WFCGP2863E5ZG","taxable_value":20087.03,"igst_amount":3683.66,"invoice_date":"2023-01-12"},"2B-00004":{"invoice_id":"2B-00004","invoice_number":"INV-2023-01-0004","supplier_gstin":"34POWGH3913A3Z3","taxable_value":56395.73,"igst_amount":6767.49,"invoice_date":"2023-01-23"},"2B-00005":{"invoice_id":"2B-00005","invoice_number":"INV-2023-01-0005","supplier_gstin":"29BQXFE3727QEZV","taxable_value":32205.98,"igst_amount":9163.2,"invoice_date":"2023-01-25"},"2B-00006":{"invoice_id":"2B-00006","invoice_number":"INV-2023-01-0006","supplier_gstin":"16HCCQP1110K9ZE","taxable_value":133475.6,"igst_amount":24025.61,"invoice_date":"2023-01-22"},"2B-00007":{"invoice_id":"2B-00007","invoice_number":"INV-2023-01-0007","supplier_gstin":"08WKAIR5223A4Z7","taxable_value":90367.34,"igst_amount":16266.12,"invoice_date":"2023-01-09"},"2B-00008":{"invoice_id":"2B-00008","invoice_number":"INV-2023-01-0008","supplier_gstin":"12VBXSS2431L5Z9","taxable_value":48784.4,"igst_amount":5854.13,"invoice_date":"2023-01-22"},"2B-00009":{"invoice_id":"2B-00009","invoice_number":"INV-2023-01-0009","supplier_gstin":"34GSACS3481WDZW","taxable_value":61695.73,"igst_amount":11105.23,"invoice_date":"2023-01-14"},"2B-00010":{"invoice_id":"2B-00010","invoice_number":"INV-2023-01-0010","supplier_gstin":"32OQUOJ3472JBZQ","taxable_value":87189.89,"igst_amount":0.0,"invoice_date":"2023-01-09"},"2B-00011":{"invoice_id":"2B-00011","invoice_number":"INV-2023-01-0011","supplier_gstin":"04ZDMSM7159CEZ5","taxable_value":54962.69,"igst_amount":14996.81,"invoice_date":"2023-01-12"},"2B-00012":{"invoice_id":"2B-00012","invoice_number":"INV-2023-01-0012","supplier_gstin":"21CLCML6402NBZ1","taxable_value":94873.0,"igst_amount":17077.14,"invoice_date":"2023-01-23"},"2B-00013":{"invoice_id":"2B-00013","invoice_number":"INV-2023-01-0013","supplier_gstin":"19TRWFG0259J8ZY","taxable_value":75816.4,"igst_amount":13646.95,"invoice_date":"2023-01-08"},"2B-00014":{"invoice_id":"2B-00014","invoice_number":"INV-2023-01-0014","supplier_gstin":"29JVKNU8587K6ZT","taxable_value":132495.12,"igst_amount":23975.95,"invoice_date":"2023-01-14"},"2B-00015":{"invoice_id":"2B-00015","invoice_number":"INV-2023-01-0015","supplier_gstin":"33RBDDD1757Y6Z1","taxable_value":124534.61,"igst_amount":28232.93,"invoice_date":"2023-01-19"},"2B-00016":{"invoice_id":"2B-00016","invoice_number":"INV-2023-01-0016","supplier_gstin":"33ZMMML1999O7ZD","taxable_value":122786.58,"igst_amount":22101.58,"invoice_date":"2023-01-06"},"2B-00017":{"invoice_id":"2B-00017","invoice_number":"INV-2023-01-0017","supplier_gstin":"09URHLL5579O4Z9","taxable_value":183689.32,"igst_amount":0.0,"invoice_date":"2023-01-22"},"2B-00018":{"invoice_id":"2B-00018","invoice_number":"INV-2023-01-0018","supplier_gstin":"10QUXMR9263U0ZU","taxable_value":39749.0,"igst_amount":2007.77,"invoice_date":"2023-01-01"},"2B-00019":{"invoice_id":"2B-00019","invoice_number":"INV-2023-01-0019","supplier_gstin":"08HCNAH3156C0ZC","taxable_value":76296.0,"igst_amount":17109.95,"invoice_date":"2023-01-04"},"2B-00020":{"invoice_id":"2B-00020","invoice_number":"INV-2023-01-0020","supplier_gstin":"04VTHVR7020REZR","taxable_value":103879.56,"igst_amount":12465.55,"invoice_date":"2023-01-20"},"2B-00021":{},"2B-00022":{"invoice_id":"2B-00022","invoice_number":"INV-2023-01-0022","supplier_gstin":"34GQSAS2374A7Z4","taxable_value":11531.89,"igst_amount":1420.53,"invoice_date":"2023-01-27"},"2B-00023":{"invoice_id":"2B-00023","invoice_number":"INV-2023-01-0023","supplier_gstin":"14CHSOG4664I0ZX","taxable_value":19369.12,"igst_amount":3486.44,"invoice_date":"2023-01-07"},"2B-00024":{"invoice_id":"2B-00024","invoice_number":"INV-2023-01-0024","supplier_gstin":"03NUITR6302QBZ9","taxable_value":196763.76,"igst_amount":35417.48,"invoice_date":"2023-01-13"},"2B-00025":{"invoice_id":"2B-00025","invoice_number":"INV-2023-01-0025","supplier_gstin":"29LPNJK2626O8ZX","taxable_value":96973.95,"igst_amount":4848.7,"invoice_date":"2023-01-08"},"2B-00026":{"invoice_id":"2B-00026","invoice_number":"INV-2023-01-0026","supplier_gstin":"05PPDFL9561L3ZG","taxable_value":132473.6,"igst_amount":0.0,"invoice_date":"2023-01-23"},"2B-00027":{"invoice_id":"2B-00027","invoice_number":"INV-2023-01-0027","supplier_gstin":"13GLGTE6203EDZ0","taxable_value":80315.12,"igst_amount":0.0,"invoice_date":"2023-01-16"},"2B-00028":{"invoice_id":"2B-00028","invoice_number":"INV-2023-01-0028","supplier_gstin":"02DRCVN4902L2ZF","taxable_value":113028.2,"igst_amount":25440.51,"invoice_date":"2023-01-28"},"2B-00029":{"invoice_id":"2B-00029","invoice_number":"INV-2023-01-0029","supplier_gstin":"15WQXIA7683QEZ2","taxable_value":91840.13,"igst_amount":15713.85,"invoice_date":"2023-01-05"}},"correct_matches":{"INV-2023-01-0000":"2B-00000","INV-2023-01-0001":"2B-00001","INV-2023-01-0002":"2B-00002","INV-2023-01-0003":"2B-00003","INV-2023-01-0004":"2B-00004","INV-2023-01-0005":"2B-00005","INV-2023-01-0006":"2B-00006","INV-2023-01-0007":"2B-00007","INV-2023-01-0008":"2B-00008","INV-2023-01-0009":"2B-00009","INV-2023-01-0010":"2B-00010","INV-2023-01-0011":"2B-00011","INV-2023-01-0012":"2B-00012","INV-2023-01-0013":"2B-00013","INV-2023-01-0014":"2B-00014","INV-2023-01-0015":"2B-00015","INV-2023-01-0016":"2B-00016","INV-2023-01-0017":"2B-00017","INV-2023-01-0018":"2B-00018","INV-2023-01-0019":"2B-00019","INV-2023-01-0020":"2B-00020","INV-2023-01-0022":"2B-00022","INV-2023-01-0023":"2B-00023","INV-2023-01-0024":"2B-00024","INV-2023-01-0025":"2B-00025","INV-2023-01-0026":"2B-00026","INV-2023-01-0027":"2B-00027","INV-2023-01-0028":"2B-00028","INV-2023-01-0029":"2B-00029"},"discrepancy_truth":{"INV-2023-01-0001":{"discrepancy_type":"amount_diff","recommended_action":"dispute"},"INV-2023-01-0003":{"discrepancy_type":"amount_diff","recommended_action":"accept_mismatch"},"INV-2023-01-0005":{"discrepancy_type":"amount_diff","recommended_action":"accept_mismatch"},"INV-2023-01-0010":{"discrepancy_type":"amount_diff","recommended_action":"dispute"},"INV-2023-01-0011":{"discrepancy_type":"amount_diff","recommended_action":"dispute"},"INV-2023-01-0014":{"discrepancy_type":"amount_diff","recommended_action":"accept_mismatch"},"INV-2023-01-0015":{"discrepancy_type":"amount_diff","recommended_action":"dispute"},"INV-2023-01-0018":{"discrepancy_type":"amount_diff","recommended_action":"accept_mismatch"},"INV-2023-01-0019":{"discrepancy_type":"amount_diff","recommended_action":"dispute"},"INV-2023-01-0021":{"discrepancy_type":"not_in_2b","correct_action_type":"defer_invoice","recommended_action":"defer"},"INV-2023-01-0022":{"discrepancy_type":"amount_diff","recommended_action":"accept_mismatch"},"INV-2023-01-0028":{"discrepancy_type":"amount_diff","recommended_action":"dispute"},"INV-2023-01-0029":{"discrepancy_type":"amount_diff","recommended_action":"dispute"}},"best_match":{"INV-2023-01-0000":"2B-00000","INV-2023-01-0001":"2B-00001","INV-2023-01-0002":"2B-00002","INV-2023-01-0003":"2B-00003","INV-2023-01-0004":"2B-00004","INV-2023-01-0005":"2B-00005","INV-2023-01-0006":"2B-00006","INV-2023-01-0007":"2B-00007","INV-2023-01-0008":"2B-00008","INV-2023-01-0009":"2B-00009","INV-2023-01-0010":"2B-00010","INV-2023-01-0011":"2B-00011","INV-2023-01-0012":"2B-00012","INV-2023-01-0013":"2B-00013","INV-2023-01-0014":"2B-00014","INV-2023-01-0015":"2B-00015","INV-2023-01-0016":"2B-00016","INV-2023-01-0017":"2B-00017","INV-2023-01-0018":"2B-00018","INV-2023-01-0019":"2B-00019","INV-2023-01-0020":"2B-00020","INV-2023-01-0022":"2B-00022","INV-2023-01-0023":"2B-00023","INV-2023-01-0024":"2B-00024","INV-2023-01-0025":"2B-00025","INV-2023-01-0026":"2B-00026","INV-2023-01-0027":"2B-00027","INV-2023-01-0028":"2B-00028","INV-2023-01-0029":"2B-00029"},"mismatches":[{"purchase_invoice_id":"INV-2023-01-0001","gstr2b_invoice_id":"2B-00001","mismatch_type":"amount_diff","purchase_taxable":21146.22,"gstr2b_taxable":-483.72,"delta":21629.94},{"purchase_invoice_id":"INV-2023-01-0003","gstr2b_invoice_id":"2B-00003","mismatch_type":"amount_diff","purchase_taxable":20464.77,"gstr2b_taxable":20087.03,"delta":377.74},{"purchase_invoice_id":"INV-2023-01-0005","gstr2b_invoice_id":"2B-00005","mismatch_type":"amount_diff","purchase_taxable":32725.71,"gstr2b_taxable":32205.98,"delta":519.73},{"purchase_invoice_id":"INV-2023-01-0010","gstr2b_invoice_id":"2B-00010","mismatch_type":"amount_diff","purchase_taxable":97474.71,"gstr2b_taxable":87189.89,"delta":10284.82},{"purchase_invoice_id":"INV-2023-01-0011","gstr2b_invoice_id":"2B-00011","mismatch_type":"amount_diff","purchase_taxable":83315.61,"gstr2b_taxable":54962.69,"delta":28352.92},{"purchase_invoice_id":"INV-2023-01-0014","gstr2b_invoice_id":"2B-00014","mismatch_type":"amount_diff","purchase_taxable":133199.71,"gstr2b_taxable":132495.12,"delta":704.59},{"purchase_invoice_id":"INV-2023-01-0015","gstr2b_invoice_id":"2B-00015","mismatch_type":"amount_diff","purchase_taxable":156849.6,"gstr2b_taxable":124534.61,"delta":32314.99},{"purchase_invoice_id":"INV-2023-01-0018","gstr2b_invoice_id":"2B-00018","mismatch_type":"amount_diff","purchase_taxable":40155.42,"gstr2b_taxable":39749.0,"delta":406.42},{"purchase_invoice_id":"INV-2023-01-0019","gstr2b_invoice_id":"2B-00019","mismatch_type":"amount_diff","purchase_taxable":95055.3,"gstr2b_taxable":76296.0,"delta":18759.3},{"purchase_invoice_id":"INV-2023-01-0021","gstr2b_invoice_id":null,"mismatch_type":"not_in_2b","purchase_taxable":129983.67,"gstr2b_taxable":null,"delta":129983.67},{"purchase_invoice_id":"INV-2023-01-0022","gstr2b_invoice_id":"2B-00022","mismatch_type":"amount_diff","purchase_taxable":11837.74,"gstr2b_taxable":11531.89,"delta":305.85},{"purchase_invoice_id":"INV-2023-01-0028","gstr2b_invoice_id":"2B-00028","mismatch_type":"amount_diff","purchase_taxable":141336.18,"gstr2b_taxable":113028.2,"delta":28307.98},{"purchase_invoice_id":"INV-2023-01-0029","gstr2b_invoice_id":"2B-00029","mismatch_type":"amount_diff","purchase_taxable":130948.79,"gstr2b_taxable":91840.13,"delta":39108.66}],"ground_truth":{"INV-2023-01-0000":{"invoice_id":"INV-2023-01-0000","invoice_type":"B2B","hsn_code":"9954","gst_slab":"18","supply_type":"services","itc_eligible":true,"reverse_charge":false},"INV-2023-01-0001":{"invoice_id":"INV-2023-01-0001","invoice_type":"B2B","hsn_code":"6601","gst_slab":"12","supply_type":"goods","itc_eligible":true,"reverse_charge":false},"INV-2023-01-0002":{"invoice_id":"INV-2023-01-0002","invoice_type":"B2B","hsn_code":"9983","gst_slab":"18","supply_type":"services","itc_eligible":true,"reverse_charge":false},"INV-2023-01-0003":{"invoice_id":"INV-2023-01-0003","invoice_type":"B2B","hsn_code":"9971","gst_slab":"18","supply_type":"services","itc_eligible":true,"reverse_charge":false},"INV-2023-01-0004":{"invoice_id":"INV-2023-01-0004","invoice_type":"B2C","hsn_code":"6601","gst_slab":"12","supply_type":"goods","itc_eligible":false,"reverse_charge":false},"INV-2023-01-0005":{"invoice_id":"INV-2023-01-0005","invoice_type":"B2B","hsn_code":"8703","gst_slab":"28","supply_type":"goods","itc_eligible":true,"reverse_charge":false},"INV-2023-01-0006":{"invoice_id":"INV-2023-01-0006","invoice_type":"B2B","hsn_code":"9988","gst_slab":"18","supply_type":"services","itc_eligible":true,"reverse_charge":false},"INV-2023-01-0007":{"invoice_id":"INV-2023-01-0007","invoice_type":"RCM","hsn_code":"9997","gst_slab":"18","supply_type":"services","itc_eligible":true,"reverse_charge":true},"INV-2023-01-0008":{"invoice_id":"INV-2023-01-0008","invoice_type":"B2B","hsn_code":"3605","gst_slab":"12","supply_type":"goods","itc_eligible":true,"reverse_charge":false},"INV-2023-01-0009":{"invoice_id":"INV-2023-01-0009","invoice_type":"B2C","hsn_code":"6401","gst_slab":"18","supply_type":"goods","itc_eligible":false,"reverse_charge":false},"INV-2023-01-0010":{"invoice_id":"INV-2023-01-0010","invoice_type":"B2B","hsn_code":"7101","gst_slab":"0","supply_type":"goods","itc_eligible":true,"reverse_charge":false},"INV-2023-01-0011":{"invoice_id":"INV-2023-01-0011","invoice_type":"B2C","hsn_code":"6401","gst_slab":"18","supply_type":"goods","itc_eligible":false,"reverse_charge":false},"INV-2023-01-0012":{"invoice_id":"INV-2023-01-0012","invoice_type":"B2B","hsn_code":"7407","gst_slab":"18","supply_type":"goods","itc_eligible":true,"reverse_charge":false},"INV-2023-01-0013":{"invoice_id":"INV-2023-01-0013","invoice_type":"EXPORT","hsn_code":"8544","gst_slab":"18","supply_type":"goods","itc_eligible":false,"reverse_charge":false},"INV-2023-01-0014":{"invoice_id":"INV-2023-01-0014","invoice_type":"B2C","hsn_code":"8443","gst_slab":"18","supply_type":"goods","itc_eligible":false,"reverse_charge":false},"INV-2023-01-0015":{"invoice_id":"INV-2023-01-0015","invoice_type":"B2B","hsn_code":"9981","gst_slab":"18","supply_type":"services","itc_eligible":true,"reverse_charge":false},"INV-2023-01-0016":{"invoice_id":"INV-2023-01-0016","invoice_type":"B2B","hsn_code":"8443","gst_slab":"18","supply_type":"goods","itc_eligible":true,"reverse_charge":false},"INV-2023-01-0017":{"invoice_id":"INV-2023-01-0017","invoice_type":"B2C","hsn_code":"4901","gst_slab":"0","supply_type":"goods","itc_eligible":false,"reverse_charge":false},"INV-2023-01-0018":{"invoice_id":"INV-2023-01-0018","invoice_type":"B2C","hsn_code":"6109","gst_slab":"5","supply_type":"goods","itc_eligible":false,"reverse_charge":false},"INV-2023-01-0019":{"invoice_id":"INV-2023-01-0019","invoice_type":"EXPORT","hsn_code":"3401","gst_slab":"18","supply_type":"goods","itc_eligible":false,"reverse_charge":false},"INV-2023-01-0020":{"invoice_id":"INV-2023-01-0020","invoice_type":"B2C","hsn_code":"8601","gst_slab":"12","supply_type":"goods","itc_eligible":false,"reverse_charge":false},"INV-2023-01-0021":{"invoice_id":"INV-2023-01-0021","invoice_type":"B2C","hsn_code":"2101","gst_slab":"18","supply_type":"goods","itc_eligible":false,"reverse_charge":false},"INV-2023-01-0022":{"invoice_id":"INV-2023-01-0022","invoice_type":"B2B","hsn_code":"9701","gst_slab":"12","supply_type":"goods","itc_eligible":true,"reverse_charge":false},"INV-2023-01-0023":{"invoice_id":"INV-2023-01-0023","invoice_type":"B2C","hsn_code":"9984","gst_slab":"18","supply_type":"services","itc_eligible":false,"reverse_charge":false},"INV-2023-01-0024":{"invoice_id":"INV-2023-01-0024","invoice_type":"RCM","hsn_code":"4016","gst_slab":"18","supply_type":"goods","itc_eligible":true,"reverse_charge":true},"INV-2023-01-0025":{"invoice_id":"INV-2023-01-0025","invoice_type":"B2B","hsn_code":"3102","gst_slab":"5","supply_type":"goods","itc_eligible":true,"reverse_charge":false},"INV-2023-01-0026":{"invoice_id":"INV-2023-01-0026","invoice_type":"B2B","hsn_code":"9993","gst_slab":"0","supply_type":"services","itc_eligible":true,"reverse_charge":false},"INV-2023-01-0027":{"invoice_id":"INV-2023-01-0027","invoice_type":"B2B","hsn_code":"0101","gst_slab":"0","supply_type":"goods","itc_eligible":true,"reverse_charge":false},"INV-2023-01-0028":{"invoice_id":"INV-2023-01-0028","invoice_type":"B2B","hsn_code":"9954","gst_slab":"18","supply_type":"services","itc_eligible":true,"reverse_charge":false},"INV-2023-01-0029":{"invoice_id":"INV-2023-01-0029","invoice_type":"B2B","hsn_code":"8601","gst_slab":"12","supply_type":"goods","itc_eligible":true,"reverse_charge":false}},"supplier_profiles":{"03FSNHI0797HCZG":{"compliance_rate":0.9106,"avg_delay_days":13.3,"cancelled_pct":0.0274},"19VNEAW9059T8ZG":{"compliance_rate":0.8533,"avg_delay_days":9.0,"cancelled_pct":0.011},"21TPHNP5763CDZ6":{"compliance_rate":0.9098,"avg_delay_days":2.4,"cancelled_pct":0.0216},"02WFCGP2863E5ZG":{"compliance_rate":0.963,"avg_delay_days":6.3,"cancelled_pct":0.0193},"34POWGH3913A3Z3":{"compliance_rate":0.87,"avg_delay_days":0.9,"cancelled_pct":0.0022},"29BQXFE3727QEZV":{"compliance_rate":0.9966,"avg_delay_days":1.7,"cancelled_pct":0.0302},"16HCCQP1110K9ZE":{"compliance_rate":0.9447,"avg_delay_days":3.2,"cancelled_pct":0.0238},"08WKAIR5223A4Z7":{"compliance_rate":0.9011,"avg_delay_days":14.7,"cancelled_pct":0.0397},"12VBXSS2431L5Z9":{"compliance_rate":0.9346,"avg_delay_days":6.0,"cancelled_pct":0.008},"34GSACS3481WDZW":{"compliance_rate":0.9629,"avg_delay_days":4.4,"cancelled_pct":0.0306},"32OQUOJ3472JBZQ":{"compliance_rate":0.9866,"avg_delay_days":3.1,"cancelled_pct":0.0133},"04ZDMSM7159CEZ5":{"compliance_rate":0.8785,"avg_delay_days":0.5,"cancelled_pct":0.0236},"21CLCML6402NBZ1":{"compliance_rate":0.8972,"avg_delay_days":4.5,"cancelled_pct":0.0128},"19TRWFG0259J8ZY":{"compliance_rate":0.9199,"avg_delay_days":1.4,"cancelled_pct":0.0466},"29JVKNU8587K6ZT":{"compliance_rate":0.8437,"avg_delay_days":10.3,"cancelled_pct":0.0143},"33RBDDD1757Y6Z1":{"compliance_rate":0.8602,"avg_delay_days":9.0,"cancelled_pct":0.0058},"33ZMMML1999O7ZD":{"compliance_rate":0.9372,"avg_delay_days":13.8,"cancelled_pct":0.0422},"09URHLL5579O4Z9":{"compliance_rate":0.936,"avg_delay_days":10.3,"cancelled_pct":0.0341},"10QUXMR9263U0ZU":{"compliance_rate":0.9701,"avg_delay_days":6.9,"cancelled_pct":0.0105},"08HCNAH3156C0ZC":{"compliance_rate":0.9596,"avg_delay_days":14.4,"cancelled_pct":0.0474},"04VTHVR7020REZR":{"compliance_rate":0.8486,"avg_delay_days":3.1,"cancelled_pct":0.0019},"19GUXPY7021M7ZY":{"compliance_rate":0.9028,"avg_delay_days":14.8,"cancelled_pct":0.0422},"34GQSAS2374A7Z4":{"compliance_rate":0.8036,"avg_delay_days":2.5,"cancelled_pct":0.0481},"14CHSOG4664I0ZX":{"compliance_rate":0.8493,"avg_delay_days":1.4,"cancelled_pct":0.0131},"03NUITR6302QBZ9":{"compliance_rate":0.8442,"avg_delay_days":14.0,"cancelled_pct":0.0241},"29LPNJK2626O8ZX":{"compliance_rate":0.9635,"avg_delay_days":2.3,"cancelled_pct":0.0476},"05PPDFL9561L3ZG":{"compliance_rate":0.8782,"avg_delay_days":10.6,"cancelled_pct":0.0064},"13GLGTE6203EDZ0":{"compliance_rate":0.9592,"avg_delay_days":13.1,"cancelled_pct":0.0353},"02DRCVN4902L2ZF":{"compliance_rate":0.9458,"avg_delay_days":7.9,"cancelled_pct":0.0225},"15WQXIA7683QEZ2":{"compliance_rate":0.9668,"avg_delay_days":11.1,"cancelled_pct":0.0498}},"eligible_itc":378563.36}}